Workbook
Name IQ_CH: 110000
Name IQ_CQ: 5000
Name IQ_CY: 10000
Name IQ_DAILY: 500000
Name IQ_FH: 100000
Name IQ_FQ: 500
Name IQ_FY: 1000
Name IQ_LTM: 2000
Name IQ_MONTH: 15000
Name IQ_NTM: 6000
Name IQ_WEEK: 50000
Name IQ_YTD: 3000

Sheet Data
A1: # | B1: Date | C1: Author | D1: Publication | E1: Title | F1: First Paragraph | G1: Anti-Semitic | H1: Not Anti-Semitic | I1: Anti-Israel | J1: Anti-Palestinian | K1: Not Anti-Palestinian | L1: Anti-Hamas | M1: Op-Ed | N1: Anti-Semtic Reason1 | O1: Anti-Semtic Reason2 | P1: title_word_count | Q1: First_Para_word_count | R1: Title_Sentiment | S1: First800_Sentiment | T1: Last4Sent_Sentiment | U1: Netanyahu_FirstPara_Sentiment | V1: Bibi_FirstPara_Sentiment | W1: Hamas_FirstPara_Sentiment | X1: Israel_FirstPara_Sentiment | Y1: Palestinian_FirstPara_Sentiment | Z1: Gaza_FirstPara_Sentiment | AA1: Ceasefire_FirstPara_Sentiment | AB1: Trump_FirstPara_Sentiment | AC1: Combined_Sentiment | AD1: text_combined_weighted | AE1: Date_dt | AF1: Date_display | AG1: Year | AH1: term1 | AI1: term2 | AJ1: term3
A2: 1 | B2: 45952 | C2: Bret Stephens | D2: The New York Times | E2: Why Mamdani Frightens Jews Like Me | F2: A recent Fox News poll found that 38 percent of Jewish New Yorkers intend to vote for Zohran Mamdani for mayor, setting aside whatever reservations they might have about the candidateâ€™s views on Israel. At least a few of those voters will support the 34-year-old state assemblyman not despite those views, but because of them | G2: 0 | H2: 0 | I2: 0 | J2: 0 | K2: 0 | L2: 0 | M2: 1 | N2: 0 | O2: 0 | P2: 6 | Q2: 55 | R2: 0.112 | S2: 0.653 | T2: 0.653 | U2: 0.5 | V2: 0.5 | W2: 0.5 | X2: 0.585 | Y2: 0.5 | Z2: 0.5 | AA2: 0.5 | AB2: 0.5 | AC2: 0.3825 | AD2: Title: Why Mamdani Frightens Jews Like Me. Title: Why Mamdani Frightens Jews Like Me. First Paragraph: A recent Fox News poll found that 38 percent of Jewish New Yorkers intend to vote for Zohran Mamdani for mayor, setting aside whatever reservations they might have about the candidateâ€™s views on Israel. At least a few of those voters will support the 34-year-old state assemblyman not despite those views, but because of them | AE2: 45952 | AF2: 45952 | AG2: 2025 | AH2: israel | AI2: jews | AJ2: hamas
A3: 2 | B3: 45944 | C3: Bret Stephens | D3: The New York Times | E3: Why Israel Won the War | F3: Though it seems absurd in retrospect, there were many in Hamas who believed their massacre of Oct. 7, 2023, would succeed not just in wounding Israel but in destroying it. | G3: 0 | H3: 0 | I3: 0 | J3: 0 | K3: 0 | L3: 0 | M3: 1 | N3: 0 | O3: 0 | P3: 5 | Q3: 30 | R3: 0.391 | S3: 0.064 | T3: 0.064 | U3: 0.5 | V3: 0.5 | W3: 0.064 | X3: 0.064 | Y3: 0.5 | Z3: 0.5 | AA3: 0.5 | AB3: 0.5 | AC3: 0.2275 | AD3: Title: Why Israel Won the War. Title: Why Israel Won the War. First Paragraph: Though it seems absurd in retrospect, there were many in Hamas who believed their massacre of Oct. 7, 2023, would succeed not just in wounding Israel but in destroying it. | AE3: 45944 | AF3: 45944 | AG3: 2025 | AH3: israel | AI3: jews | AJ3: hamas
A4: 3 | B4: 45937 | C4: Bret Stephens | D4: The New York Times | E4: What Israel Should Learn From Two Years of War | F4: Maya Angelouâ€™s classic warning should have been believed in 1988, when Hamas declared in its founding covenant its intention to slaughter Jews. Instead, Israel continued to tolerate Hamas out of a combination of ideological convenience â€” it suited Benjamin Netanyahu, the Israeli prime minister, to have a divided Palestinian polity â€” and international reluctance to topple the group. That was until Oct. 7, 2023, too late for the 1,200 people slaughtered that day. | G4: 0 | H4: 0 | I4: 0 | J4: 0 | K4: 0 | L4: 0 | M4: 1 | N4: 0 | O4: 0 | P4: 9 | Q4: 73 | R4: 0.181 | S4: 0.204 | T4: 0.204 | U4: 0.131 | V4: 0.5 | W4: 0.208 | X4: 0.131 | Y4: 0.131 | Z4: 0.5 | AA4: 0.5 | AB4: 0.5 | AC4: 0.1925 | AD4: Title: What Israel Should Learn From Two Years of War. Title: What Israel Should Learn From Two Years of War. First Paragraph: Maya Angelouâ€™s classic warning should have been believed in 1988, when Hamas declared in its founding covenant its intention to slaughter Jews. Instead, Israel continued to tolerate Hamas out of a combination of ideological convenience â€” it suited Benjamin Netanyahu, the Israeli prime minister, to have a divided Palestinian polity â€” and international reluctance to topple the group. That was until Oct. 7, 2023, too late for the 1,200 people slaughtered that day. | AE4: 45937 | AF4: 45937 | AG4: 2025 | AH4: israel | AI4: jews | AJ4: hamas
A5: 4 | B5: 45909 | C5: Bret Stephens | D5: The New York Times | E5: Gesture Politics Wonâ€™t Help Palestinians | F5: This month, France, Canada, Australia and possibly Britain will recognize a Palestinian state at the United Nations General Assembly. Also, some 1,800 actors and filmmakers, including Mark Ruffalo and Cynthia Nixon, have signed a public letter pledging â€œnot to screen films, appear at or otherwise work with Israeli film institutions.â€ And the government of Spain imposed an arms embargo on Israel. | G5: 0 | H5: 0 | I5: 0 | J5: 0 | K5: 0 | L5: 0 | M5: 1 | N5: 0 | O5: 0 | P5: 5 | Q5: 61 | R5: 0.059 | S5: 0.475 | T5: 0.475 | U5: 0.5 | V5: 0.5 | W5: 0.5 | X5: 0.142 | Y5: 0.564 | Z5: 0.5 | AA5: 0.5 | AB5: 0.5 | AC5: 0.267 | AD5: Title: Gesture Politics Wonâ€™t Help Palestinians. Title: Gesture Politics Wonâ€™t Help Palestinians. First Paragraph: This month, France, Canada, Australia and possibly Britain will recognize a Palestinian state at the United Nations General Assembly. Also, some 1,800 actors and filmmakers, including Mark Ruffalo and Cynthia Nixon, have signed a public letter pledging â€œnot to screen films, appear at or otherwise work with Israeli film institutions.â€ And the government of Spain imposed an arms embargo on Israel. | AE5: 45909 | AF5: 45909 | AG5: 2025 | AH5: israel | AI5: jews | AJ5: hamas
A6: 5 | B6: 45874 | C6: Bret Stephens | D6: The New York Times | E6: Where Can Gaza Go From Here? | F6: First and most obviously: The government of Israel needs to rush, in abundant quantities and to immediate and undeniable effect, food and medicine to the places in Gaza that desperately need them. | G6: 0 | H6: 0 | I6: 0 | J6: 0 | K6: 0 | L6: 0 | M6: 1 | N6: 0 | O6: 0 | P6: 6 | Q6: 32 | R6: 0.29 | S6: 0.349 | T6: 0.349 | U6: 0.5 | V6: 0.5 | W6: 0.5 | X6: 0.349 | Y6: 0.5 | Z6: 0.349 | AA6: 0.5 | AB6: 0.5 | AC6: 0.3195 | AD6: Title: Where Can Gaza Go From Here?. Title: Where Can Gaza Go From Here?. First Paragraph: First and most obviously: The government of Israel needs to rush, in abundant quantities and to immediate and undeniable effect, food and medicine to the places in Gaza that desperately need them. | AE6: 45874 | AF6: 45874 | AG6: 2025 | AH6: israel | AI6: jews | AJ6: hamas
A7: 6 | B7: 45860 | C7: Bret Stephens | D7: The New York Times | E7: No, Israel Is Not Committing Genocide in Gaza | F7: It may seem harsh to say, but there is a glaring dissonance to the charge that Israel is committing genocide in Gaza. To wit: If the Israeli governmentâ€™s intentions and actions are truly genocidal â€” if it is so malevolent that it is committed to the annihilation of Gazans â€” why hasnâ€™t it been more methodical and vastly more deadly? Why not, say, hundreds of thousands of deaths, as opposed to the nearly 60,000 that Gazaâ€™s Hamas-run Health Ministry, which does not distinguish between combatant and civilian deaths, has cited so far in nearly two years of war? | G7: 0 | H7: 0 | I7: 0 | J7: 0 | K7: 0 | L7: 0 | M7: 1 | N7: 0 | O7: 0 | P7: 8 | Q7: 98 | R7: 0.19 | S7: 0.099 | T7: 0.099 | U7: 0.5 | V7: 0.5 | W7: 0.114 | X7: 0.069 | Y7: 0.5 | Z7: 0.092 | AA7: 0.5 | AB7: 0.5 | AC7: 0.1445 | AD7: Title: No, Israel Is Not Committing Genocide in Gaza. Title: No, Israel Is Not Committing Genocide in Gaza. First Paragraph: It may seem harsh to say, but there is a glaring dissonance to the charge that Israel is committing genocide in Gaza. To wit: If the Israeli governmentâ€™s intentions and actions are truly genocidal â€” if it is so malevolent that it is committed to the annihilation of Gazans â€” why hasnâ€™t it been more methodical and vastly more deadly? Why not, say, hundreds of thousands of deaths, as opposed to the nearly 60,000 that Gazaâ€™s Hamas-run Health Ministry, which does not distinguish between combatant and civilian deaths, has cited so far in nearly two years of war? | AE7: 45860 | AF7: 45860 | AG7: 2025 | AH7: israel | AI7: jews | AJ7: hamas
A8: 7 | B8: 45846 | C8: Bret Stephens | D8: The New York Times | E8: For Israel, It Pays to Be a Winner | F8: A core misconception about Israelâ€™s policy since Oct. 7 is that the country has favored military action at the expense of diplomacy. The truth is that itâ€™s Israelâ€™s decisive battlefield victories that have created diplomatic openings that have been out of reach for decades â€” and would have remained so if Israel hadnâ€™t won. | G8: 0 | H8: 0 | I8: 0 | J8: 0 | K8: 0 | L8: 0 | M8: 1 | N8: 0 | O8: 0 | P8: 8 | Q8: 54 | R8: 0.686 | S8: 0.256 | T8: 0.256 | U8: 0.5 | V8: 0.5 | W8: 0.5 | X8: 0.256 | Y8: 0.5 | Z8: 0.5 | AA8: 0.5 | AB8: 0.5 | AC8: 0.471 | AD8: Title: For Israel, It Pays to Be a Winner. Title: For Israel, It Pays to Be a Winner. First Paragraph: A core misconception about Israelâ€™s policy since Oct. 7 is that the country has favored military action at the expense of diplomacy. The truth is that itâ€™s Israelâ€™s decisive battlefield victories that have created diplomatic openings that have been out of reach for decades â€” and would have remained so if Israel hadnâ€™t won. | AE8: 45846 | AF8: 45846 | AG8: 2025 | AH8: israel | AI8: jews | AJ8: hamas
A9: 8 | B9: 45839 | C9: Bret Stephens | D9: The New York Times | E9: What â€˜Globalize the Intifadaâ€™ Really Means | F9: Zohran Mamdani got three chances to repudiate the expression â€œglobalize the intifadaâ€ in a weekend interview with NBCâ€™s Kristen Welker. It would have been easy, and politically smart, for the Democratic candidate for New York mayor to say that heâ€™d been educated about the phraseâ€™s violent connotation and that he regretted not rejecting it sooner. Instead, he ducked each time, saying that although he does not use those words himself, he would decline to â€œpoliceâ€ the language of others. | G9: 0 | H9: 0 | I9: 0 | J9: 0 | K9: 0 | L9: 0 | M9: 1 | N9: 0 | O9: 0 | P9: 6 | Q9: 79 | R9: 0.286 | S9: 0.339 | T9: 0.339 | U9: 0.5 | V9: 0.5 | W9: 0.5 | X9: 0.5 | Y9: 0.5 | Z9: 0.5 | AA9: 0.5 | AB9: 0.5 | AC9: 0.3125 | AD9: Title: What â€˜Globalize the Intifadaâ€™ Really Means. Title: What â€˜Globalize the Intifadaâ€™ Really Means. First Paragraph: Zohran Mamdani got three chances to repudiate the expression â€œglobalize the intifadaâ€ in a weekend interview with NBCâ€™s Kristen Welker. It would have been easy, and politically smart, for the Democratic candidate for New York mayor to say that heâ€™d been educated about the phraseâ€™s violent connotation and that he regretted not rejecting it sooner. Instead, he ducked each time, saying that although he does not use those words himself, he would decline to â€œpoliceâ€ the language of others. | AE9: 45839 | AF9: 45839 | AG9: 2025 | AH9: israel | AI9: jews | AJ9: hamas
A10: 9 | B10: 45821 | C10: Bret Stephens | D10: The New York Times | E10: Israel Had the Courage to Do What Needed to Be Done | F10: It may be months or years before weâ€™ll know the full results of Israelâ€™s attack on Iranian nuclear and military targets, which began early Friday morning and could last for days or weeks. But critics of the strike â€” and already they are vocal â€” might at least ask themselves whether Israel had any realistic alternative against an adversary that has repeatedly vowed to wipe it off the map. | G10: 0 | H10: 0 | I10: 0 | J10: 0 | K10: 0 | L10: 0 | M10: 1 | N10: 0 | O10: 0 | P10: 11 | Q10: 69 | R10: 0.647 | S10: 0.157 | T10: 0.157 | U10: 0.5 | V10: 0.5 | W10: 0.5 | X10: 0.157 | Y10: 0.5 | Z10: 0.5 | AA10: 0.5 | AB10: 0.5 | AC10: 0.402 | AD10: Title: Israel Had the Courage to Do What Needed to Be Done. Title: Israel Had the Courage to Do What Needed to Be Done. First Paragraph: It may be months or years before weâ€™ll know the full results of Israelâ€™s attack on Iranian nuclear and military targets, which began early Friday morning and could last for days or weeks. But critics of the strike â€” and already they are vocal â€” might at least ask themselves whether Israel had any realistic alternative against an adversary that has repeatedly vowed to wipe it off the map. | AE10: 45821 | AF10: 45821 | AG10: 2025 | AH10: israel | AI10: jews | AJ10: hamas
A11: 10 | B11: 45748 | C11: Bret Stephens | D11: The New York Times | E11: Here Is the Real Route to Freeing Palestinians | F11: The world should remember the name of Odai Al-Rubai. The 22-year-old Palestinian man joined protests in Gaza last week to demand an end to 18 years of Hamasâ€™s violent misrule in the territory. Demonstrators could be heard shouting, â€œOut, out, Hamas, get outâ€ and â€œHamas are terrorists,â€ while displaying banners saying, â€œHamas does not represent us.â€ In retaliation, Al-Rubaiâ€™s family says, he was kidnapped, tortured and murdered by members of Hamasâ€™s Qassam Brigades. Then his body was dumped in front of the family home. | G11: 0 | H11: 0 | I11: 0 | J11: 0 | K11: 0 | L11: 0 | M11: 1 | N11: 0 | O11: 0 | P11: 8 | Q11: 84 | R11: 0.485 | S11: 0.285 | T11: 0.285 | U11: 0.5 | V11: 0.5 | W11: 0.079 | X11: 0.5 | Y11: 0.226 | Z11: 0.226 | AA11: 0.5 | AB11: 0.5 | AC11: 0.385 | AD11: Title: Here Is the Real Route to Freeing Palestinians. Title: Here Is the Real Route to Freeing Palestinians. First Paragraph: The world should remember the name of Odai Al-Rubai. The 22-year-old Palestinian man joined protests in Gaza last week to demand an end to 18 years of Hamasâ€™s violent misrule in the territory. Demonstrators could be heard shouting, â€œOut, out, Hamas, get outâ€ and â€œHamas are terrorists,â€ while displaying banners saying, â€œHamas does not represent us.â€ In retaliation, Al-Rubaiâ€™s family says, he was kidnapped, tortured and murdered by members of Hamasâ€™s Qassam Brigades. Then his body was dumped in front of the family home. | AE11: 45748 | AF11: 45748 | AG11: 2025 | AH11: israel | AI11: jews | AJ11: hamas
A12: 11 | B12: 45715 | C12: Bret Stephens | D12: The New York Times | E12: Earth to Barnard College: Enough | F12: The pro-Palestinian mob is back in Manhattanâ€™s Morningside Heights. So are the Hamas-friendly chants of â€œintifada revolutionâ€ and posts about â€œresistance until return.â€ So is the bullying and violence. | G12: 0 | H12: 0 | I12: 0 | J12: 0 | K12: 0 | L12: 0 | M12: 1 | N12: 0 | O12: 0 | P12: 5 | Q12: 29 | R12: 0.489 | S12: 0.065 | T12: 0.065 | U12: 0.5 | V12: 0.5 | W12: 0.046 | X12: 0.5 | Y12: 0.289 | Z12: 0.5 | AA12: 0.5 | AB12: 0.5 | AC12: 0.277 | AD12: Title: Earth to Barnard College: Enough. Title: Earth to Barnard College: Enough. First Paragraph: The pro-Palestinian mob is back in Manhattanâ€™s Morningside Heights. So are the Hamas-friendly chants of â€œintifada revolutionâ€ and posts about â€œresistance until return.â€ So is the bullying and violence. | AE12: 45715 | AF12: 45715 | AG12: 2025 | AH12: israel | AI12: jews | AJ12: hamas
A13: 12 | B13: 45699 | C13: Bret Stephens | D13: The New York Times | E13: The Horror Show of Hamas Must End Now | F13: On Saturday, Hamas gunmen paraded three skeletally thin Israeli hostages for a propaganda video in which they were forced to thank their captors before their handover to the Red Cross. One of the hostages, Eli Sharabi, returned to Israel to learn that his wife, Lianne, and their teenage daughters, Noiya and Yahel, had been murdered on Oct. 7. | G13: 0 | H13: 0 | I13: 0 | J13: 0 | K13: 0 | L13: 0 | M13: 1 | N13: 0 | O13: 0 | P13: 8 | Q13: 58 | R13: 0.052 | S13: 0.135 | T13: 0.135 | U13: 0.5 | V13: 0.5 | W13: 0.156 | X13: 0.095 | Y13: 0.5 | Z13: 0.5 | AA13: 0.5 | AB13: 0.5 | AC13: 0.0935 | AD13: Title: The Horror Show of Hamas Must End Now. Title: The Horror Show of Hamas Must End Now. First Paragraph: On Saturday, Hamas gunmen paraded three skeletally thin Israeli hostages for a propaganda video in which they were forced to thank their captors before their handover to the Red Cross. One of the hostages, Eli Sharabi, returned to Israel to learn that his wife, Lianne, and their teenage daughters, Noiya and Yahel, had been murdered on Oct. 7. | AE13: 45699 | AF13: 45699 | AG13: 2025 | AH13: israel | AI13: jews | AJ13: hamas
... A84: 83 | B84: 45947 | C84: Isabel Kershner | D84: The New York Times | E84: After â€˜Horrors,â€™ Israeli Hostages Taste Freedom and Savor Family Reunions | F84: Some former captives have been sent home from the hospital. But a doctor said they all had â€œendured untold adversity,â€ as details emerge of their time in Gazaâ€™s tunnels. Eitan Horn, a freed hostage in his late 30s, lost about half his body weight and was forced to walk for about 12 hours through the tunnels beneath Gaza when his captors wanted to move him, his sister-in-law, Dalia Cusnir, said in an interview. | G84: 0 | H84: 0 | I84: 0 | J84: 0 | K84: 0 | L84: 0 | M84: 0 | N84: 0 | O84: 0 | P84: 10 | Q84: 73 | R84: 0.498 | S84: 0.288 | T84: 0.288 | U84: 0.5 | V84: 0.5 | W84: 0.5 | X84: 0.5 | Y84: 0.5 | Z84: 0.252 | AA84: 0.5 | AB84: 0.5 | AC84: 0.393 | AD84: Title: After â€˜Horrors,â€™ Israeli Hostages Taste Freedom and Savor Family Reunions. Title: After â€˜Horrors,â€™ Israeli Hostages Taste Freedom and Savor Family Reunions. First Paragraph: Some former captives have been sent home from the hospital. But a doctor said they all had â€œendured untold adversity,â€ as details emerge of their time in Gazaâ€™s tunnels. Eitan Horn, a freed hostage in his late 30s, lost about half his body weight and was forced to walk for about 12 hours through the tunnels beneath Gaza when his captors wanted to move him, his sister-in-law, Dalia Cusnir, said in an interview. | AE84: 45947 | AF84: 45947 | AG84: 2025 | AH84: israeli | AI84: israel | AJ84: gaza
A85: 84 | B85: 45947 | C85: John Yoon | D85: The New York Times | E85: U.S. Says Louisiana Man Joined Hamas-Led 2023 Attack on Israel | F85: The man appeared in court on Friday morning, after federal prosecutors accused him of joining Gazan militants in attacking Israel and lying to obtain a U.S. visa. Federal prosecutors in Louisiana accused a man of participating in the Hamas-led October 2023 attack on Israel and then traveling to the United States on a fraudulent visa, according to a criminal complaint unsealed this week. | G85: 0 | H85: 0 | I85: 0 | J85: 0 | K85: 0 | L85: 0 | M85: 0 | N85: 0 | O85: 0 | P85: 10 | Q85: 63 | R85: 0.186 | S85: 0.194 | T85: 0.194 | U85: 0.5 | V85: 0.5 | W85: 0.18 | X85: 0.194 | Y85: 0.5 | Z85: 0.5 | AA85: 0.5 | AB85: 0.5 | AC85: 0.19 | AD85: Title: U.S. Says Louisiana Man Joined Hamas-Led 2023 Attack on Israel. Title: U.S. Says Louisiana Man Joined Hamas-Led 2023 Attack on Israel. First Paragraph: The man appeared in court on Friday morning, after federal prosecutors accused him of joining Gazan militants in attacking Israel and lying to obtain a U.S. visa. Federal prosecutors in Louisiana accused a man of participating in the Hamas-led October 2023 attack on Israel and then traveling to the United States on a fraudulent visa, according to a criminal complaint unsealed this week. | AE85: 45947 | AF85: 45947 | AG85: 2025 | AH85: hamas led | AI85: 2023 attack | AJ85: 2023
A86: 85 | B86: 45947 | C86: Ezra Klein | D86: The New York Times | E86: Two Middle East Negotiators Assess Trumpâ€™s Israel-Hamas Deal | F86: On Oct. 9, the Israeli government voted to ratify an agreement between Israel and Hamas brokered by the Trump administration, Qatar and Turkey that, it is hoped, finally brings an end to the conflict. This deal has already led to the release of the remaining 20 Israeli hostages. Their coming home was an incredibly emotional thing to watch. | G86: 0 | H86: 0 | I86: 0 | J86: 0 | K86: 0 | L86: 0 | M86: 1 | N86: 0 | O86: 0 | P86: 8 | Q86: 58 | R86: 0.493 | S86: 0.83 | T86: 0.83 | U86: 0.5 | V86: 0.5 | W86: 0.67 | X86: 0.67 | Y86: 0.5 | Z86: 0.5 | AA86: 0.5 | AB86: 0.67 | AC86: 0.6615 | AD86: Title: Two Middle East Negotiators Assess Trumpâ€™s Israel-Hamas Deal. Title: Two Middle East Negotiators Assess Trumpâ€™s Israel-Hamas Deal. First Paragraph: On Oct. 9, the Israeli government voted to ratify an agreement between Israel and Hamas brokered by the Trump administration, Qatar and Turkey that, it is hoped, finally brings an end to the conflict. This deal has already led to the release of the remaining 20 Israeli hostages. Their coming home was an incredibly emotional thing to watch. | AE86: 45947 | AF86: 45947 | AG86: 2025 | AH86: negotiators | AI86: trump | AJ86: deal
A87: 86 | B87: 45947 | C87: Dana Stroul | D87: The New York Times | E87: The Real Trump Factor in the Gaza Deal | F87: Praise for President Trumpâ€™s diplomacy in brokering a cease-fire in Gaza has mostly focused on how he persuaded Prime Minister Benjamin Netanyahu of Israel to accept a deal. Many assume that Mr. Trump threatened to withdraw U.S. support from Israel or otherwise pressured the Israeli leader into capitulating. But there is a more convincing explanation for Mr. Trumpâ€™s success. Far from merely menacing Mr. Netanyahu with consequences, the American presidentâ€™s key intervention was to give a political lifeline to the deeply unpopular Israeli leader. The secret of Mr. Trumpâ€™s success with Mr. Netanyahu was offering carrots on domestic politics, not sticks on foreign policy. | G87: 0 | H87: 0 | I87: 0 | J87: 0 | K87: 0 | L87: 0 | M87: 1 | N87: 0 | O87: 0 | P87: 8 | Q87: 104 | R87: 0.392 | S87: 0.773 | T87: 0.465 | U87: 0.824 | V87: 0.5 | W87: 0.5 | X87: 0.735 | Y87: 0.5 | Z87: 0.91 | AA87: 0.5 | AB87: 0.793 | AC87: 0.5825 | AD87: Title: The Real Trump Factor in the Gaza Deal. Title: The Real Trump Factor in the Gaza Deal. First Paragraph: Praise for President Trumpâ€™s diplomacy in brokering a cease-fire in Gaza has mostly focused on how he persuaded Prime Minister Benjamin Netanyahu of Israel to accept a deal. Many assume that Mr. Trump threatened to withdraw U.S. support from Israel or otherwise pressured the Israeli leader into capitulating. But there is a more convincing explanation for Mr. Trumpâ€™s success. Far from merely menacing Mr. Netanyahu with consequences, the American presidentâ€™s key intervention was to give a political lifeline to the deeply unpopular Israeli leader. The secret of Mr. Trumpâ€™s success with Mr. Netanyahu was offering carrots on domestic politics, not sticks on foreign policy. | AE87: 45947 | AF87: 45947 | AG87: 2025 | AH87: trump | AI87: factor | AJ87: success
A88: 87 | B88: 45946 | C88: Emma Fitzsimmons | D88: The New York Times | E88: Mamdani Faces Vitriolic Attacks After Comments About Hamas | F88: Zohran Mamdani, the front-runner in the race for mayor of New York City, was criticized by lawmakers from both parties after he dodged a question about Hamasâ€™s future. His campaign denounced the attacks as Islamophobic. Zohran Mamdani, the Democratic nominee for mayor of New York City, faced vitriolic attacks that suggested he was a terrorist sympathizer after he gave an indirect answer to a question on Wednesday about whether Hamas should lay down arms and step aside in Gaza. President Trump said on Thursday that if Hamas continued to kill people in Gaza, â€œwe will have no choice but to go in and kill them,â€ a stark warning after Hamas fighters were captured on video in recent days executing members of rival groups in the Palestinian territory. | G88: 0 | H88: 0 | I88: 0 | J88: 0 | K88: 1 | L88: 0 | M88: 0 | N88: 0 | O88: 0 | P88: 8 | Q88: 127 | R88: 0.129 | S88: 0.134 | T88: 0.134 | U88: 0.5 | V88: 0.5 | W88: 0.141 | X88: 0.5 | Y88: 0.101 | Z88: 0.113 | AA88: 0.5 | AB88: 0.101 | AC88: 0.1315 | AD88: Title: Mamdani Faces Vitriolic Attacks After Comments About Hamas. Title: Mamdani Faces Vitriolic Attacks After Comments About Hamas. First Paragraph: Zohran Mamdani, the front-runner in the race for mayor of New York City, was criticized by lawmakers from both parties after he dodged a question about Hamasâ€™s future. His campaign denounced the attacks as Islamophobic. Zohran Mamdani, the Democratic nominee for mayor of New York City, faced vitriolic attacks that suggested he was a terrorist sympathizer after he gave an indirect answer to a question on Wednesday about whether Hamas should lay down arms and step aside in Gaza. President Trump said on Thursday that if Hamas continued to kill people in Gaza, â€œwe will have no choice but to go in and kill them,â€ a stark warning after Hamas fighters were captured on video in recent days executing members of rival groups in the Palestinian territory. | AE88: 45946 | AF88: 45946 | AG88: 2025 | AH88: attacks | AI88: question | AJ88: comments
A89: 88 | B89: 45946 | C89: Zolan Kanno-Youngs | D89: The New York Times | E89: Trump Warns Hamas of Strikes if Violence in Gaza Continues | F89: The president later clarified that the United States would not be involved in such an action. President Trump said on Thursday that if Hamas continued to kill people in Gaza, â€œwe will have no choice but to go in and kill them,â€ a stark warning after Hamas fighters were captured on video in recent days executing members of rival groups in the Palestinian territory. | G89: 0 | H89: 0 | I89: 0 | J89: 0 | K89: 0 | L89: 1 | M89: 0 | N89: 0 | O89: 0 | P89: 10 | Q89: 64 | R89: 0.114 | S89: 0.246 | T89: 0.246 | U89: 0.5 | V89: 0.5 | W89: 0.101 | X89: 0.5 | Y89: 0.101 | Z89: 0.101 | AA89: 0.5 | AB89: 0.101 | AC89: 0.18 | AD89: Title: Trump Warns Hamas of Strikes if Violence in Gaza Continues. Title: Trump Warns Hamas of Strikes if Violence in Gaza Continues. First Paragraph: The president later clarified that the United States would not be involved in such an action. President Trump said on Thursday that if Hamas continued to kill people in Gaza, â€œwe will have no choice but to go in and kill them,â€ a stark warning after Hamas fighters were captured on video in recent days executing members of rival groups in the Palestinian territory. | AE89: 45946 | AF89: 45946 | AG89: 2025 | AH89: warns | AI89: trump | AJ89: kill
A90: 89 | B90: 45946 | C90: Jonathan Wolfe | D90: The New York Times | E90: Hacked Airport P.A. Systems Broadcast Anti-Trump and Pro-Hamas Messages | F90: The hacks at four North American airports raised fresh concerns over the security of noncritical but highly visible airport infrastructure. The airports said the disruption was minimal. The public address systems at four airports in North America were hacked on Tuesday and used to broadcast messages praising Hamas and criticizing President Trump, officials said. | G90: 0 | H90: 0 | I90: 0 | J90: 0 | K90: 1 | L90: 0 | M90: 0 | N90: 0 | O90: 0 | P90: 9 | Q90: 54 | R90: 0.243 | S90: 0.22 | T90: 0.22 | U90: 0.5 | V90: 0.5 | W90: 0.233 | X90: 0.5 | Y90: 0.5 | Z90: 0.5 | AA90: 0.5 | AB90: 0.233 | AC90: 0.2315 | AD90: Title: Hacked Airport P.A. Systems Broadcast Anti-Trump and Pro-Hamas Messages. Title: Hacked Airport P.A. Systems Broadcast Anti-Trump and Pro-Hamas Messages. First Paragraph: The hacks at four North American airports raised fresh concerns over the security of noncritical but highly visible airport infrastructure. The airports said the disruption was minimal. The public address systems at four airports in North America were hacked on Tuesday and used to broadcast messages praising Hamas and criticizing President Trump, officials said. | AE90: 45946 | AF90: 45946 | AG90: 2025 | AH90: airport | AI90: systems | AJ90: broadcast
A91: 90 | B91: 45946 | C91: Shuaib Almosawa | D91: The New York Times | E91: Yemenâ€™s Houthis Confirm Killing of Top Military Official | F91: It was unclear when Maj. Gen. Mohammed al-Ghomari was killed, or by whom, but Israel appeared to claim the killing. The Houthi militia in Yemen said on Thursday that a senior military official had been killed, in what it described as an â€œIsraeli-Americanâ€ airstrike, without disclosing when. | G91: 0 | H91: 0 | I91: 0 | J91: 0 | K91: 0 | L91: 0 | M91: 0 | N91: 0 | O91: 0 | P91: 8 | Q91: 47 | R91: 0.119 | S91: 0.228 | T91: 0.228 | U91: 0.5 | V91: 0.5 | W91: 0.5 | X91: 0.28 | Y91: 0.5 | Z91: 0.5 | AA91: 0.5 | AB91: 0.5 | AC91: 0.1735 | AD91: Title: Yemenâ€™s Houthis Confirm Killing of Top Military Official. Title: Yemenâ€™s Houthis Confirm Killing of Top Military Official. First Paragraph: It was unclear when Maj. Gen. Mohammed al-Ghomari was killed, or by whom, but Israel appeared to claim the killing. The Houthi militia in Yemen said on Thursday that a senior military official had been killed, in what it described as an â€œIsraeli-Americanâ€ airstrike, without disclosing when. | AE91: 45946 | AF91: 45946 | AG91: 2025 | AH91: yemen | AI91: top military | AJ91: confirm
A92: 91 | B92: 45946 | C92: Ephrat Livni | D92: The New York Times | E92: Where Does the Israel-Hamas Cease-Fire Stand? | F92: Unresolved issues and flare-ups of violence threaten to destabilize the fragile agreement. The cease-fire between Israel and Hamas has held for more than a week. But each side has accused the other of violating the agreement, which rests on shaky ground, and there are unresolved issues that put the future of the truce at risk. | G92: 0 | H92: 0 | I92: 0 | J92: 0 | K92: 0 | L92: 0 | M92: 0 | N92: 0 | O92: 0 | P92: 6 | Q92: 55 | R92: 0.437 | S92: 0.085 | T92: 0.085 | U92: 0.5 | V92: 0.5 | W92: 0.212 | X92: 0.212 | Y92: 0.5 | Z92: 0.5 | AA92: 0.5 | AB92: 0.5 | AC92: 0.261 | AD92: Title: Where Does the Israel-Hamas Cease-Fire Stand?. Title: Where Does the Israel-Hamas Cease-Fire Stand?. First Paragraph: Unresolved issues and flare-ups of violence threaten to destabilize the fragile agreement. The cease-fire between Israel and Hamas has held for more than a week. But each side has accused the other of violating the agreement, which rests on shaky ground, and there are unresolved issues that put the future of the truce at risk. | AE92: 45946 | AF92: 45946 | AG92: 2025 | AH92: role | AI92: red cross | AJ92: video
A93: 92 | B93: 45946 | C93: Natan Odenheimer | D93: The New York Times | E93: A Day of Somber Ceremony in Israel, With a Fragile Cease-Fire Holding | F93: Ceremonies took place on Thursday to commemorate two years since the surprise attack of Oct. 7, 2023, on southern Israel. Israel marked a national day of commemoration on Thursday for the victims of the Hamas-led Oct. 7, 2023, attack on southern Israel, and for those who died in the ensuing war, almost a week after a cease-fire in Gaza was declared. | G93: 0 | H93: 0 | I93: 0 | J93: 0 | K93: 0 | L93: 0 | M93: 0 | N93: 0 | O93: 0 | P93: 12 | Q93: 61 | R93: 0.441 | S93: 0.595 | T93: 0.595 | U93: 0.5 | V93: 0.5 | W93: 0.423 | X93: 0.595 | Y93: 0.5 | Z93: 0.423 | AA93: 0.5 | AB93: 0.5 | AC93: 0.518 | AD93: Title: A Day of Somber Ceremony in Israel, With a Fragile Cease-Fire Holding. Title: A Day of Somber Ceremony in Israel, With a Fragile Cease-Fire Holding. First Paragraph: Ceremonies took place on Thursday to commemorate two years since the surprise attack of Oct. 7, 2023, on southern Israel. Israel marked a national day of commemoration on Thursday for the victims of the Hamas-led Oct. 7, 2023, attack on southern Israel, and for those who died in the ensuing war, almost a week after a cease-fire in Gaza was declared. | AE93: 45946 | AF93: 45946 | AG93: 2025 | AH93: cease fire | AI93: cease | AJ93: fire
A94: 93 | B94: 45946 | C94: M. Gessen | D94: The New York Times | E94: Her Optimism Has Won Her Some of the Most Powerful Enemies in the World | F94: Albanese became a hometown hero after the White House branded her an enemy, which it did because of her work, over the past three years, as the United Nations special rapporteur for the occupied Palestinian territories. In the course of that work, she has pursued strategies that are as legally ambitious as they are politically risky. She has documented human rights abuses, as her predecessors did. She infuriated some of her allies by condemning the Hamas violence of Oct. 7, 2023, then caused a storm when she leaped onto social media to contest a boilerplate statement by the president of France that framed the violence as antisemitic. Perhaps most explosively, she has called out the corporations, including some of the largest in the United States, that enable and benefit from human rights abuses, and which are likely to continue to do so, regardless of the cease-fire. | G94: 0 | H94: 0 | I94: 0 | J94: 0 | K94: 0 | L94: 0 | M94: 1 | N94: 0 | O94: 0 | P94: 14 | Q94: 146 | R94: 0.884 | S94: 0.396 | T94: 0.293 | U94: 0.5 | V94: 0.5 | W94: 0.06 | X94: 0.5 | Y94: 0.522 | Z94: 0.5 | AA94: 0.5 | AB94: 0.5 | AC94: 0.64 | AD94: Title: Her Optimism Has Won Her Some of the Most Powerful Enemies in the World. Title: Her Optimism Has Won Her Some of the Most Powerful Enemies in the World. First Paragraph: Albanese became a hometown hero after the White House branded her an enemy, which it did because of her work, over the past three years, as the United Nations special rapporteur for the occupied Palestinian territories. In the course of that work, she has pursued strategies that are as legally ambitious as they are politically risky. She has documented human rights abuses, as her predecessors did. She infuriated some of her allies by condemning the Hamas violence of Oct. 7, 2023, then caused a storm when she leaped onto social media to contest a boilerplate statement by the president of France that framed the violence as antisemitic. Perhaps most explosively, she has called out the corporations, including some of the largest in the United States, that enable and benefit from human rights abuses, and which are likely to continue to do so, regardless of the cease-fire. | AE94: 45946 | AF94: 45946 | AG94: 2025 | AH94: abuses | AI94: enemies | AJ94: won
A95: 94 | B95: 45945 | C95: Nicholas Kristoff | D95: The New York Times | E95: What Lies Ahead in the Middle East Isnâ€™t Right vs. Wrong. Itâ€™s Right vs. Right. | F95: My keyboard, so used to criticisms of President Trump, is shocked as I hammer out this column. But Trump genuinely deserves great credit for (belatedly) ramming through the Gaza cease-fire and release of hostages and detainees. Bravo, Mr. President. Yet what lies ahead is more prayer than plan, and to make this a lasting peace it would help if we all discarded the Manichaean paradigm of good versus evil that many Westerners apply to Israelis and Palestinians (while disagreeing on who gets which label), making compromise difficult or impossible. To make progress, it may help to think of the conflict not in terms of right versus wrong, but of right versus right. | G95: 1 | H95: 0 | I95: 0 | J95: 0 | K95: 0 | L95: 0 | M95: 1 | N95: 0 | O95: 1 | P95: 15 | Q95: 112 | R95: 0.272 | S95: 0.77 | T95: 0.938 | U95: 0.5 | V95: 0.5 | W95: 0.5 | X95: 0.5 | Y95: 0.5 | Z95: 0.751 | AA95: 0.5 | AB95: 0.549 | AC95: 0.521 | AD95: Title: What Lies Ahead in the Middle East Isnâ€™t Right vs. Wrong. Itâ€™s Right vs. Right.. Title: What Lies Ahead in the Middle East Isnâ€™t Right vs. Wrong. Itâ€™s Right vs. Right.. First Paragraph: My keyboard, so used to criticisms of President Trump, is shocked as I hammer out this column. But Trump genuinely deserves great credit for (belatedly) ramming through the Gaza cease-fire and release of hostages and detainees. Bravo, Mr. President. Yet what lies ahead is more prayer than plan, and to make this a lasting peace it would help if we all discarded the Manichaean paradigm of good versus evil that many Westerners apply to Israelis and Palestinians (while disagreeing on who gets which label), making compromise difficult or impossible. To make progress, it may help to think of the conflict not in terms of right versus wrong, but of right versus right. | AE95: 45945 | AF95: 45945 | AG95: 2025 | AH95: right | AI95: lies | AJ95: wrong
A96: 95 | B96: 45945 | C96: Ephrat Livni | D96: The New York Times | E96: Hamas Says It Has Returned All Hostage Remains It Can Recover | F96: The militants said they would need special equipment to retrieve more bodies in Gaza. The announcement could put the truce with Israel at risk. Hamasâ€™s military wing, the Qassam Brigades, said on Wednesday night that it had handed over all of the remains of Israeli hostages that it had been able to recover without additional equipment, potentially putting a cease-fire with Israel in the Gaza Strip at risk. | G96: 1 | H96: 0 | I96: 0 | J96: 0 | K96: 0 | L96: 0 | M96: 0 | N96: 0 | O96: 1 | P96: 11 | Q96: 68 | R96: 0.576 | S96: 0.161 | T96: 0.161 | U96: 0.5 | V96: 0.5 | W96: 0.286 | X96: 0.171 | Y96: 0.5 | Z96: 0.218 | AA96: 0.5 | AB96: 0.5 | AC96: 0.3685 | AD96: Title: Hamas Says It Has Returned All Hostage Remains It Can Recover. Title: Hamas Says It Has Returned All Hostage Remains It Can Recover. First Paragraph: The militants said they would need special equipment to retrieve more bodies in Gaza. The announcement could put the truce with Israel at risk. Hamasâ€™s military wing, the Qassam Brigades, said on Wednesday night that it had handed over all of the remains of Israeli hostages that it had been able to recover without additional equipment, potentially putting a cease-fire with Israel in the Gaza Strip at risk. | AE96: 45945 | AF96: 45945 | AG96: 2025 | AH96: role | AI96: red cross | AJ96: video
A97: 96 | B97: 45945 | C97: Andrew Ross | D97: The New York Times | E97: The Israel-Gaza War Always Had an Unacknowledged Third Front | F97: Nothing can undo the staggering loss of life and the bloodshed of the attacks of Oct. 7, 2023, the relentless bombardment and starvation of Gazans and the increasing violence directed against West Bank communities. But amid the prospects of a lasting cease-fire and Palestinian self-determination, there must also be pressure to end the unsparing detention of the thousands of Palestinians who continue to be held in Israelâ€™s prisons, many under conditions that defy international laws mandating humane treatment of detainees. | G97: 0 | H97: 0 | I97: 0 | J97: 0 | K97: 0 | L97: 0 | M97: 1 | N97: 0 | O97: 0 | P97: 9 | Q97: 80 | R97: 0.245 | S97: 0.101 | T97: 0.101 | U97: 0.5 | V97: 0.5 | W97: 0.5 | X97: 0.419 | Y97: 0.419 | Z97: 0.5 | AA97: 0.5 | AB97: 0.5 | AC97: 0.173 | AD97: Title: The Israel-Gaza War Always Had an Unacknowledged Third Front. Title: The Israel-Gaza War Always Had an Unacknowledged Third Front. First Paragraph: Nothing can undo the staggering loss of life and the bloodshed of the attacks of Oct. 7, 2023, the relentless bombardment and starvation of Gazans and the increasing violence directed against West Bank communities. But amid the prospects of a lasting cease-fire and Palestinian self-determination, there must also be pressure to end the unsparing detention of the thousands of Palestinians who continue to be held in Israelâ€™s prisons, many under conditions that defy international laws mandating humane treatment of detainees. | AE97: 45945 | AF97: 45945 | AG97: 2025 | AH97: israel gaza war | AI97: always | AJ97: third
... A201: 200 | B201: 45236 | C201: Nick Cumming-Bruce | D201: The New York Times | E201: U.N. Says Israel-Gaza War Is Deadliest Ever for Its Personnel | F201: The U.N. secretary general, AntÃ³nio Guterres, said Monday that 89 employees of UNRWA, its agency aiding Palestinian refugees, had been killed since the war began. The United Nations secretary general, AntÃ³nio Guterres, said on Monday that 89 employees of the U.N. agency aiding Palestinian refugees, known as UNRWA, had been killed in Gaza in the month of war between Israel and Hamas. That is more â€œthan in any comparable period in the history of our organization,â€ he told reporters at U.N. headquarters in New York, adding that many of the employees had been killed with members of their family. The United Nations employs large numbers of Palestinians in Gaza, where almost half the working-age population is unemployed. On Sunday, the leaders of United Nations agencies and other humanitarian groups issued a joint statement calling for an immediate cease-fire, saying, â€œEnough is enough. This must stop now.â€ In the statement, they expressed â€œshock and horrorâ€ at the loss of life and called for the immediate release of hostages taken during the Hamas attacks in Israel last month. They noted that â€œmore than 100 attacks against health careâ€ had been reported and that â€œscores of aid workersâ€ had been killed since the attacks and Israelâ€™s retaliatory airstrikes on Gaza. Of the loss of U.N. staff members, Juliette Touma, a spokeswoman for UNRWA, said: â€œThe number goes up every day.â€ â€œThey are killed in the north, the middle and the south, men and women, some at home, some at displacement shelters, some bringing refugees to the shelters,â€ she added. One staff member was killed as he waited in line for bread, she said, and another was killed at home with his wife and eight children. Most worked in the agencyâ€™s schools in Gaza, she said. The World Health Organization said 16 health care workers had died while on duty in Gaza, and the International Federation of Red Cross and Red Crescent Societies said its member organizations had lost seven staff members in the war. The fatalities, the International Federation of Red Cross and Red Crescent Societies said, included three medical staff of Magen David Adom, Israelâ€™s emergency medical service, who were killed as they tried to rescue people from the kibbutzim under attack by Hamas and take them to the hospital. | G201: 0 | H201: 0 | I201: 0 | J201: 0 | K201: 0 | L201: 1 | M201: 0 | N201: 0 | O201: 0 | P201: 10 | Q201: 378 | R201: 0.079 | S201: 0.184 | T201: 0.097 | U201: 0.5 | V201: 0.5 | W201: 0.098 | X201: 0.089 | Y201: 0.163 | Z201: 0.11 | AA201: 0.5 | AB201: 0.5 | AC201: 0.1315 | AD201: Title: U.N. Says Israel-Gaza War Is Deadliest Ever for Its Personnel. Title: U.N. Says Israel-Gaza War Is Deadliest Ever for Its Personnel. First Paragraph: The U.N. secretary general, AntÃ³nio Guterres, said Monday that 89 employees of UNRWA, its agency aiding Palestinian refugees, had been killed since the war began. The United Nations secretary general, AntÃ³nio Guterres, said on Monday that 89 employees of the U.N. agency aiding Palestinian refugees, known as UNRWA, had been killed in Gaza in the month of war between Israel and Hamas. That is more â€œthan in any comparable period in the history of our organization,â€ he told reporters at U.N. headquarters in New York, adding that many of the employees had been killed with members of their family. The United Nations employs large numbers of Palestinians in Gaza, where almost half the working-age population is unemployed. On Sunday, the leaders of United Nations agencies and other humanitarian groups issued a joint statement calling for an immediate cease-fire, saying, â€œEnough is enough. This must stop now.â€ In the statement, they expressed â€œshock and horrorâ€ at the loss of life and called for the immediate release of hostages taken during the Hamas attacks in Israel last month. They noted that â€œmore than 100 attacks against health careâ€ had been reported and that â€œscores of aid workersâ€ had been killed since the attacks and Israelâ€™s retaliatory airstrikes on Gaza. Of the loss of U.N. staff members, Juliette Touma, a spokeswoman for UNRWA, said: â€œThe number goes up every day.â€ â€œThey are killed in the north, the middle and the south, men and women, some at home, some at displacement shelters, some bringing refugees to the shelters,â€ she added. One staff member was killed as he waited in line for bread, she said, and another was killed at home with his wife and eight children. Most worked in the agencyâ€™s schools in Gaza, she said. The World Health Organization said 16 health care workers had died while on duty in Gaza, and the International Federation of Red Cross and Red Crescent Societies said its member organizations had lost seven staff members in the war. The fatalities, the International Federation of Red Cross and Red Crescent Societies said, included three medical staff of Magen David Adom, Israelâ€™s emergency medical service, who were killed as they tried to rescue people from the kibbutzim under attack by Hamas and take them to the hospital. | AE201: 45236 | AF201: 45236 | AG201: 2023 | AH201: killed | AI201: staff | AJ201: refugees
A202: 201 | B202: 45234 | C202: Lisa Lerer | D202: The New York Times | E202: Obama Urges Americans to Take in â€˜Whole Truthâ€™ of Israel-Gaza War | F202: The former president said everyone was â€œcomplicit to some degreeâ€ in the current bloodshed and acknowledged the points of view on both sides of the conflict. Barack Obama offered a complex analysis of the conflict between Israel and Gaza, telling thousands of former aides that they were all â€œcomplicit to some degreeâ€ in the current bloodshed. â€œI look at this, and I think back, â€˜What could I have done during my presidency to move this forward, as hard as I tried?â€™â€ he said in an interview conducted by his former staffers for their podcast, Pod Save America. â€œBut thereâ€™s a part of me thatâ€™s still saying, â€˜Well, was there something else I could have done?â€™â€ Mr. Obama entered the White House convinced he could be the president who would resolve the decades-old conflict between Israelis and Palestinians. He left office after years of friction and mistrust with Prime Minister Benjamin Netanyahu of Israel, who was frustrated by the presidentâ€™s masterminding of the Iran nuclear deal and by his demands that Israel suspend new settlements. In his comments on Friday, delivered at a gathering of his former staff in Chicago, Mr. Obama acknowledged the strong emotions the war had raised, saying that â€œthis is century-old stuff thatâ€™s coming to the fore.â€ He blamed social media for amplifying the divisions and reducing a thorny international dispute to what he viewed as sloganeering. Yet he urged his former aides to â€œtake in the whole truth,â€ seemingly attempting to strike a balance between the killings on both sides. â€œWhat Hamas did was horrific, and thereâ€™s no justification for it,â€ Mr. Obama said. â€œAnd what is also true is that the occupation and whatâ€™s happening to Palestinians is unbearable.â€ He continued: â€œAnd what is also true is that there is a history of the Jewish people that may be dismissed unless your grandparents or your great-grandparents, or your uncle or your aunt tell you stories about the madness of antisemitism. And what is true is that there are people right now who are dying, who have nothing to do with what Hamas did.â€ Still, Mr. Obama appeared to acknowledge the limits of his musings about bridging divides and embracing complexity. â€œEven what I just said, which sounds very persuasive, still doesnâ€™t answer the fact of, all right, how do we prevent kids from being killed today?â€ he said. â€œBut the problem is that if you are dug in on that, well, the other side is dug in remembering the videos that Hamas took or what they did on the 7th, and theyâ€™re dug in, too, which means we will not stop those kids from dying.â€ | G202: 1 | H202: 0 | I202: 1 | J202: 0 | K202: 0 | L202: 1 | M202: 0 | N202: 1 | O202: 1 | P202: 11 | Q202: 440 | R202: 0.505 | S202: 0.412 | T202: 0.164 | U202: 0.182 | V202: 0.5 | W202: 0.112 | X202: 0.243 | Y202: 0.5 | Z202: 0.299 | AA202: 0.5 | AB202: 0.5 | AC202: 0.4585 | AD202: Title: Obama Urges Americans to Take in â€˜Whole Truthâ€™ of Israel-Gaza War. Title: Obama Urges Americans to Take in â€˜Whole Truthâ€™ of Israel-Gaza War. First Paragraph: The former president said everyone was â€œcomplicit to some degreeâ€ in the current bloodshed and acknowledged the points of view on both sides of the conflict. Barack Obama offered a complex analysis of the conflict between Israel and Gaza, telling thousands of former aides that they were all â€œcomplicit to some degreeâ€ in the current bloodshed. â€œI look at this, and I think back, â€˜What could I have done during my presidency to move this forward, as hard as I tried?â€™â€ he said in an interview conducted by his former staffers for their podcast, Pod Save America. â€œBut thereâ€™s a part of me thatâ€™s still saying, â€˜Well, was there something else I could have done?â€™â€ Mr. Obama entered the White House convinced he could be the president who would resolve the decades-old conflict between Israelis and Palestinians. He left office after years of friction and mistrust with Prime Minister Benjamin Netanyahu of Israel, who was frustrated by the presidentâ€™s masterminding of the Iran nuclear deal and by his demands that Israel suspend new settlements. In his comments on Friday, delivered at a gathering of his former staff in Chicago, Mr. Obama acknowledged the strong emotions the war had raised, saying that â€œthis is century-old stuff thatâ€™s coming to the fore.â€ He blamed social media for amplifying the divisions and reducing a thorny international dispute to what he viewed as sloganeering. Yet he urged his former aides to â€œtake in the whole truth,â€ seemingly attempting to strike a balance between the killings on both sides. â€œWhat Hamas did was horrific, and thereâ€™s no justification for it,â€ Mr. Obama said. â€œAnd what is also true is that the occupation and whatâ€™s happening to Palestinians is unbearable.â€ He continued: â€œAnd what is also true is that there is a history of the Jewish people that may be dismissed unless your grandparents or your great-grandparents, or your uncle or your aunt tell you stories about the madness of antisemitism. And what is true is that there are people right now who are dying, who have nothing to do with what Hamas did.â€ Still, Mr. Obama appeared to acknowledge the limits of his musings about bridging divides and embracing complexity. â€œEven what I just said, which sounds very persuasive, still doesnâ€™t answer the fact of, all right, how do we prevent kids from being killed today?â€ he said. â€œBut the problem is that if you are dug in on that, well, the other side is dug in remembering the videos that Hamas took or what they did on the 7th, and theyâ€™re dug in, too, which means we will not stop those kids from dying.â€ | AE202: 45234 | AF202: 45234 | AG202: 2023 | AH202: former | AI202: truth | AJ202: TRUE
A203: 202 | B203: 45238 | C203: Eric Schmitt | D203: The New York Times | E203: U.S. Strikes Iran-Linked Facility in Syria in Round of Retaliation | F203: Drone and rocket attacks on U.S. forces have continued in recent weeks, prompting a second round of retaliatory airstrikes in eastern Syria. For the second time in nearly two weeks, the United States carried out airstrikes against a facility used by Iranâ€™s Islamic Revolutionary Guards Corps and its proxies in eastern Syria early Thursday, ratcheting up retaliation for a steady stream of rocket and drone attacks against American forces in Iraq and Syria. The strikes by two Air Force F-15E jets against a weapons warehouse in Deir al Zour Province, Syria, came after U.S. airstrikes on Oct. 27 against similar targets in eastern Syria failed to deter Iran or its proxies in Syria and Iraq, which the Biden administration has blamed for the attacks. Not only have the attacks continued â€” there have been at least 22 more since the American retaliatory strikes last month â€” but Pentagon officials said they have become more dangerous. Iran-backed militias have packed even larger loads of explosives â€” more than 80 pounds â€” onto drones launched at American bases, U.S. officials said. â€œThis precision self-defense strike is a response to a series of attacks against U.S. personnel in Iraq and Syria by I.R.G.C.-Quds Force affiliates,â€ Defense Secretary Lloyd J. Austin III said in a statement. â€œThe president has no higher priority than the safety of U.S. personnel, and he directed todayâ€™s action to make clear that the United States will defend itself, its personnel, and its interests.â€ â€œThe United States is fully prepared to take further necessary measures to protect our people and our facilities,â€ he added. â€œWe urge against any escalation.â€ The strikes also came after the Pentagon said a U.S. military MQ-9 Reaper surveillance drone was shot down over the Red Sea off the coast of Yemen on Wednesday by Iran-backed Houthi rebels. The downing of the drone, the mainstay of the American militaryâ€™s aerial surveillance fleet, was another escalation of violence between the United States and Iran-backed groups in the region. The episode underscored the risks that the conflict between Israel and the Palestinian group Hamas could spiral into a wider war. Biden administration officials have been trying to calculate how to deter the Iranian-backed Shiite militias from attacking American troops in the region without sparking that broader conflict, said three administration officials, who spoke on the condition of anonymity to discuss internal planning. â€œThe attacks, the threats coming from militia that are aligned with Iran, are totally unacceptable,â€ Secretary of State Antony J. Blinken said in Iraq on Sunday. The Pentagon said on Wednesday that there had been at least 41 attacks on U.S. forces in Syria and Iraq since Oct. 17 and that at least 46 U.S. service members had been injured, 25 of whom had suffered traumatic brain injuries. The United States has 2,500 troops in Iraq and 900 in Syria, mostly to help local forces fight remnants of the Islamic State. In meetings to select targets, U.S. officials try to game out what response each strike will bring, one official said. Military officials at the Pentagonâ€™s Central Command and in the American intelligence community have a good idea where many militia leaders are, two officials said, and have, in the past two weeks, considered the possible blowback if targeted airstrikes were to kill those leaders. The effort to calibrate retaliation is inexact, the officials acknowledged. The strike against the weapons warehouse early Thursday was aimed at â€œdisrupting and degradingâ€ the abilities of the militias to carry out attacks against American troops, a senior Pentagon official told reporters after the strike. But the strike was carried out late at night in Syria when the chances of hitting any Iranian personnel or militia fighters were small, Pentagon officials said. | G203: 0 | H203: 0 | I203: 0 | J203: 0 | K203: 0 | L203: 0 | M203: 0 | N203: 0 | O203: 0 | P203: 10 | Q203: 621 | R203: 0.368 | S203: 0.191 | T203: 0.448 | U203: 0.5 | V203: 0.5 | W203: 0.073 | X203: 0.073 | Y203: 0.073 | Z203: 0.5 | AA203: 0.5 | AB203: 0.5 | AC203: 0.2795 | AD203: Title: U.S. Strikes Iran-Linked Facility in Syria in Round of Retaliation. Title: U.S. Strikes Iran-Linked Facility in Syria in Round of Retaliation. First Paragraph: Drone and rocket attacks on U.S. forces have continued in recent weeks, prompting a second round of retaliatory airstrikes in eastern Syria. For the second time in nearly two weeks, the United States carried out airstrikes against a facility used by Iranâ€™s Islamic Revolutionary Guards Corps and its proxies in eastern Syria early Thursday, ratcheting up retaliation for a steady stream of rocket and drone attacks against American forces in Iraq and Syria. The strikes by two Air Force F-15E jets against a weapons warehouse in Deir al Zour Province, Syria, came after U.S. airstrikes on Oct. 27 against similar targets in eastern Syria failed to deter Iran or its proxies in Syria and Iraq, which the Biden administration has blamed for the attacks. Not only have the attacks continued â€” there have been at least 22 more since the American retaliatory strikes last month â€” but Pentagon officials said they have become more dangerous. Iran-backed militias have packed even larger loads of explosives â€” more than 80 pounds â€” onto drones launched at American bases, U.S. officials said. â€œThis precision self-defense strike is a response to a series of attacks against U.S. personnel in Iraq and Syria by I.R.G.C.-Quds Force affiliates,â€ Defense Secretary Lloyd J. Austin III said in a statement. â€œThe president has no higher priority than the safety of U.S. personnel, and he directed todayâ€™s action to make clear that the United States will defend itself, its personnel, and its interests.â€ â€œThe United States is fully prepared to take further necessary measures to protect our people and our facilities,â€ he added. â€œWe urge against any escalation.â€ The strikes also came after the Pentagon said a U.S. military MQ-9 Reaper surveillance drone was shot down over the Red Sea off the coast of Yemen on Wednesday by Iran-backed Houthi rebels. The downing of the drone, the mainstay of the American militaryâ€™s aerial surveillance fleet, was another escalation of violence between the United States and Iran-backed groups in the region. The episode underscored the risks that the conflict between Israel and the Palestinian group Hamas could spiral into a wider war. Biden administration officials have been trying to calculate how to deter the Iranian-backed Shiite militias from attacking American troops in the region without sparking that broader conflict, said three administration officials, who spoke on the condition of anonymity to discuss internal planning. â€œThe attacks, the threats coming from militia that are aligned with Iran, are totally unacceptable,â€ Secretary of State Antony J. Blinken said in Iraq on Sunday. The Pentagon said on Wednesday that there had been at least 41 attacks on U.S. forces in Syria and Iraq since Oct. 17 and that at least 46 U.S. service members had been injured, 25 of whom had suffered traumatic brain injuries. The United States has 2,500 troops in Iraq and 900 in Syria, mostly to help local forces fight remnants of the Islamic State. In meetings to select targets, U.S. officials try to game out what response each strike will bring, one official said. Military officials at the Pentagonâ€™s Central Command and in the American intelligence community have a good idea where many militia leaders are, two officials said, and have, in the past two weeks, considered the possible blowback if targeted airstrikes were to kill those leaders. The effort to calibrate retaliation is inexact, the officials acknowledged. The strike against the weapons warehouse early Thursday was aimed at â€œdisrupting and degradingâ€ the abilities of the militias to carry out attacks against American troops, a senior Pentagon official told reporters after the strike. But the strike was carried out late at night in Syria when the chances of hitting any Iranian personnel or militia fighters were small, Pentagon officials said. | AE203: 45238 | AF203: 45238 | AG203: 2023 | AH203: syria | AI203: pentagon | AJ203: iran
A204: 203 | B204: 45233 | C204: Ben Hubbard | D204: The New York Times | E204: In High-Stakes Speech, Hezbollahâ€™s Leader Stops Short of Call to Expand Hamas War | F204: In his first public comments since the war in Gaza began, Hassan Nasrallah said his powerful Lebanese militia had bogged down Israeli forces to help Hamas. Since the war in Gaza began after Hamasâ€™s surprise attack on Israel on Oct. 7, people across the Middle East have feared it could set off a second war between Israel and Hezbollah, the powerful Lebanese militia, and ignite a broader regional conflagration. That is not Hezbollahâ€™s plan, the groupâ€™s leader, Hassan Nasrallah, said in a widely anticipated address to his followers on Friday, his first public remarks since the start of the war. He warned, however, that Hezbollahâ€™s forces were ready for anything. Hezbollah, he said, was already doing what it set out to do: exchanging fire with a portion of Israelâ€™s military to keep it tied up along the northern border with Lebanon, reducing the burden on Hamas. â€œThe Lebanese front has lessened a large part of the forces that were going to escalate the attack on Gaza,â€ Mr. Nasrallah said. â€œSome in Lebanon say that we are taking a risk, itâ€™s true. But this risk is part of a beneficial, correct calculation.â€ But he added that he was keeping Hezbollahâ€™s forces prepared should hostilities with Israel escalate. â€œAll the possibilities on our Lebanese front are open,â€ he said. â€œAll the choices are available and we could resort to them at any time.â€ Israel and Hezbollah have clashed repeatedly along the Israel-Lebanon border since the war began, targeting each otherâ€™s positions and killing combatants on both sides. Mr. Nasrallahâ€™s address, which lasted more than an hour and repeatedly erupted into fiery crescendos, was far from a call for peace. But it fit with analystsâ€™ assessment that Israel and Hezbollah appeared to be calibrating their actions to avoid setting off a broader war. Mr. Nasrallah described Hezbollahâ€™s objective as a controlled battle along the border aimed at sapping Israel's morale and resources. That message was most likely a disappointment to Hamas, a Hezbollah ally that is also supported by Iran, some of whose leaders have called on their regional partners to do more in the fight against Israel. Israel, the United States and other countries consider both groups terrorist organizations. During one of the most tense periods in the Middle East in recent years, though, Mr. Nasrallahâ€™s speech offered a small measure of relief for many, that at least one powerful force was not seeking to plunge the region into even greater violence. Hezbollah is a more powerful and sophisticated military force than Hamas, with tens of thousands of trained fighters, an arsenal of more than 100,000 rockets and a stock of precision-guided missiles that can strike sensitive targets deep inside Israel. Military analysts believe that the group may also have other military capabilities that it has yet to unveil. Mr. Nasrallah is a highly respected figure inside a group that calls itself the â€œaxis of resistance,â€ a network of Iranian-backed militias in several Arab countries that share an anti-American and anti-Israeli ideology and have come to coordinate their operations more closely in recent years. A decision by Hezbollah to launch a full-on war with Israel would most likely encourage attacks by an assortment of allied militias in Iraq, Syria and Yemen. During his address, which was live-streamed to large gatherings of Hezbollah supporters around Lebanon, Mr. Nasrallah lashed out at the United States for its staunch support for Israel, accusing President Biden of dishonesty in telling Israel that it had the right to defend itself but that it had to respect human rights. â€œEmpty talk! Hypocrisy!â€ Mr. Nasrallah boomed. He also said the group was not intimidated by the two aircraft carriers that the United States had dispatched to the eastern Mediterranean, which could strike Hezbollah targets. â€œYour fleets in the Mediterranean do not scare us and will never scare us,â€ Mr. Nasrallah said. â€œYour fleets that you threaten us with, we are prepared for them as well.â€ Should the United States intervene directly in the war, Mr. Nasrallah said, it could expect attacks by Hezbollahâ€™s allies on its military bases and other targets in Iraq, Syria and elsewhere. The U.S. military has said the carriers were sent to deter a wider regional war â€” a fear that has grown alongside mounting anger in Arab countries over the crisis facing Gazan civilians and the death toll in the strip, which has risen into the many thousands since Israelâ€™s bombardment began. Israel has faced increasing international criticism over the dire conditions in Gaza, but has so far resisted calls for either a cease-fire or humanitarian â€œpausesâ€ to help deliver aid. Mr. Nasrallah praised the fighters from his and other armed groups in Lebanon, saying they were launching daily attacks on Israeli military positions and destroying communications infrastructure. Those attacks had forced Israeli civilians to flee and drawn Israeli military resources to the north so that they could not contribute to attacks on Gaza. He acknowledged that the possibility of a regional war still existed, but said that it could be avoided if Israel halted its attacks on Gaza. Thousands of Hezbollah supporters gathered to watch the speech on giant screens in locations throughout Lebanon. The largest site, in Beirutâ€™s southern suburbs, was decorated with Hezbollah and Palestinian flags. Celebratory gunfire rang out when he appeared onscreen, and supporters chanted, â€œWe are here for you, Nasrallah.â€ Early in the speech, Mr. Nasrallah praised Hamas for carrying out the Oct. 7 attack, which included assaults on large groups of civilians and killed more than 1,400 people in Israel. The Hezbollah leader said that no battle was more justified from a religious, moral or humanitarian perspective than â€œthe battle with these Zionists.â€ He said that Israeli treatment of the Palestinians had gotten so bad that a â€œgreat eventâ€ had been required to restore the Palestinian cause as â€œthe No. 1 issue in the world.â€ In Beirut, Mohamad Sbeti, 40, fired a volley of celebratory gunshots into the air with a pistol after Mr. Nasrallah finished speaking. He said he would answer any call by Hezbollah to fight Israel. â€œWe donâ€™t want war,â€ he said. â€œBut if war comes, me, my two boys and my wife will go and fight.â€ A driver who had grown poorer during Lebanonâ€™s deep economic crisis in recent years, Mr. Sbeti was not overly worried about the vast damage that Israel could do to Lebanon in a new war. â€œWhy should I be afraid?â€ he said. â€œWe have nothing to lose.â€ | G204: 1 | H204: 0 | I204: 0 | J204: 0 | K204: 1 | L204: 0 | M204: 0 | N204: 1 | O204: 1 | P204: 13 | Q204: 1079 | R204: 0.461 | S204: 0.251 | T204: 0.291 | U204: 0.5 | V204: 0.5 | W204: 0.275 | X204: 0.264 | Y204: 0.428 | Z204: 0.236 | AA204: 0.5 | AB204: 0.5 | AC204: 0.356 | AD204: Title: In High-Stakes Speech, Hezbollahâ€™s Leader Stops Short of Call to Expand Hamas War. Title: In High-Stakes Speech, Hezbollahâ€™s Leader Stops Short of Call to Expand Hamas War. First Paragraph: In his first public comments since the war in Gaza began, Hassan Nasrallah said his powerful Lebanese militia had bogged down Israeli forces to help Hamas. Since the war in Gaza began after Hamasâ€™s surprise attack on Israel on Oct. 7, people across the Middle East have feared it could set off a second war between Israel and Hezbollah, the powerful Lebanese militia, and ignite a broader regional conflagration. That is not Hezbollahâ€™s plan, the groupâ€™s leader, Hassan Nasrallah, said in a widely anticipated address to his followers on Friday, his first public remarks since the start of the war. He warned, however, that Hezbollahâ€™s forces were ready for anything. Hezbollah, he said, was already doing what it set out to do: exchanging fire with a portion of Israelâ€™s military to keep it tied up along the northern border with Lebanon, reducing the burden on Hamas. â€œThe Lebanese front has lessened a large part of the forces that were going to escalate the attack on Gaza,â€ Mr. Nasrallah said. â€œSome in Lebanon say that we are taking a risk, itâ€™s true. But this risk is part of a beneficial, correct calculation.â€ But he added that he was keeping Hezbollahâ€™s forces prepared should hostilities with Israel escalate. â€œAll the possibilities on our Lebanese front are open,â€ he said. â€œAll the choices are available and we could resort to them at any time.â€ Israel and Hezbollah have clashed repeatedly along the Israel-Lebanon border since the war began, targeting each otherâ€™s positions and killing combatants on both sides. Mr. Nasrallahâ€™s address, which lasted more than an hour and repeatedly erupted into fiery crescendos, was far from a call for peace. But it fit with analystsâ€™ assessment that Israel and Hezbollah appeared to be calibrating their actions to avoid setting off a broader war. Mr. Nasrallah described Hezbollahâ€™s objective as a controlled battle along the border aimed at sapping Israel's morale and resources. That message was most likely a disappointment to Hamas, a Hezbollah ally that is also supported by Iran, some of whose leaders have called on their regional partners to do more in the fight against Israel. Israel, the United States and other countries consider both groups terrorist organizations. During one of the most tense periods in the Middle East in recent years, though, Mr. Nasrallahâ€™s speech offered a small measure of relief for many, that at least one powerful force was not seeking to plunge the region into even greater violence. Hezbollah is a more powerful and sophisticated military force than Hamas, with tens of thousands of trained fighters, an arsenal of more than 100,000 rockets and a stock of precision-guided missiles that can strike sensitive targets deep inside Israel. Military analysts believe that the group may also have other military capabilities that it has yet to unveil. Mr. Nasrallah is a highly respected figure inside a group that calls itself the â€œaxis of resistance,â€ a network of Iranian-backed militias in several Arab countries that share an anti-American and anti-Israeli ideology and have come to coordinate their operations more closely in recent years. A decision by Hezbollah to launch a full-on war with Israel would most likely encourage attacks by an assortment of allied militias in Iraq, Syria and Yemen. During his address, which was live-streamed to large gatherings of Hezbollah supporters around Lebanon, Mr. Nasrallah lashed out at the United States for its staunch support for Israel, accusing President Biden of dishonesty in telling Israel that it had the right to defend itself but that it had to respect human rights. â€œEmpty talk! Hypocrisy!â€ Mr. Nasrallah boomed. He also said the group was not intimidated by the two aircraft carriers that the United States had dispatched to the eastern Mediterranean, which could strike Hezbollah targets. â€œYour fleets in the Mediterranean do not scare us and will never scare us,â€ Mr. Nasrallah said. â€œYour fleets that you threaten us with, we are prepared for them as well.â€ Should the United States intervene directly in the war, Mr. Nasrallah said, it could expect attacks by Hezbollahâ€™s allies on its military bases and other targets in Iraq, Syria and elsewhere. The U.S. military has said the carriers were sent to deter a wider regional war â€” a fear that has grown alongside mounting anger in Arab countries over the crisis facing Gazan civilians and the death toll in the strip, which has risen into the many thousands since Israelâ€™s bombardment began. Israel has faced increasing international criticism over the dire conditions in Gaza, but has so far resisted calls for either a cease-fire or humanitarian â€œpausesâ€ to help deliver aid. Mr. Nasrallah praised the fighters from his and other armed groups in Lebanon, saying they were launching daily attacks on Israeli military positions and destroying communications infrastructure. Those attacks had forced Israeli civilians to flee and drawn Israeli military resources to the north so that they could not contribute to attacks on Gaza. He acknowledged that the possibility of a regional war still existed, but said that it could be avoided if Israel halted its attacks on Gaza. Thousands of Hezbollah supporters gathered to watch the speech on giant screens in locations throughout Lebanon. The largest site, in Beirutâ€™s southern suburbs, was decorated with Hezbollah and Palestinian flags. Celebratory gunfire rang out when he appeared onscreen, and supporters chanted, â€œWe are here for you, Nasrallah.â€ Early in the speech, Mr. Nasrallah praised Hamas for carrying out the Oct. 7 attack, which included assaults on large groups of civilians and killed more than 1,400 people in Israel. The Hezbollah leader said that no battle was more justified from a religious, moral or humanitarian perspective than â€œthe battle with these Zionists.â€ He said that Israeli treatment of the Palestinians had gotten so bad that a â€œgreat eventâ€ had been required to restore the Palestinian cause as â€œthe No. 1 issue in the world.â€ In Beirut, Mohamad Sbeti, 40, fired a volley of celebratory gunshots into the air with a pistol after Mr. Nasrallah finished speaking. He said he would answer any call by Hezbollah to fight Israel. â€œWe donâ€™t want war,â€ he said. â€œBut if war comes, me, my two boys and my wife will go and fight.â€ A driver who had grown poorer during Lebanonâ€™s deep economic crisis in recent years, Mr. Sbeti was not overly worried about the vast damage that Israel could do to Lebanon in a new war. â€œWhy should I be afraid?â€ he said. â€œWe have nothing to lose.â€ | AE204: 45233 | AF204: 45233 | AG204: 2023 | AH204: hezbollah | AI204: nasrallah | AJ204: lebanon
A205: 204 | B205: 45233 | C205: Mark Landler | D205: The New York Times | E205: As Gaza War Enters New Phase, Israel Faces Pressure Over Civilian Deaths | F205: Fears are rising that the conflict could spread to the occupied West Bank, where tensions are soaring among Palestinians angered over deadly Israeli airstrikes in Gaza. Nearly a week after Israeli tanks and troops poured into Gaza, Israeli military officials say they have made steady gains against Hamas. But the ground operation, which now encircles Gaza City, is entering an acutely perilous phase, with Israeli troops advancing in an urban landscape that is honeycombed with tunnels and home to many Palestinians. Israeli airstrikes this week on a densely populated neighborhood in northern Gaza that have killed scores of civilians are fueling fears that the war could spread to a second front: the much larger occupied West Bank, where Palestinians have been enraged by the bombardment, which has killed thousands. Harrowing images of the dead and wounded are also intensifying international pressure on Israel. On Friday, Secretary of State Antony J. Blinken pressed Prime Minister Benjamin Netanyahu to order â€œhumanitarian pausesâ€ in the operation to allow more aid to reach civilians and more people to leave the strip. But Mr. Netanyahu later appeared to reject the idea of pausing the military campaign, saying that any cease-fire would depend on the freeing of Israeli hostages held by Hamas in Gaza. One senior Israeli military official said he was confident that the troops would seize control of Gaza, and Israel claims to have killed hundreds of Hamas militants in its assaults. But the official was not sure, with global public opinion turning sharply against Israel, that they would have enough time to root out all of the Hamas forces â€” a push that Israeli leaders have said could take months. Publicly, Israeli commanders are claiming steady gains, but offering few details, about their military response to the Hamas attacks of Oct. 7, which left 1,400 soldiers and civilians dead, including women, children and older people and which included torture and abuse. â€œOur forces are at the heart of a ground operation in the north of the Gaza Strip,â€ Lt. Gen. Herzi Halevi, the Israeli military chief of staff, said in a statement on Thursday. â€œWeâ€™re encircling Gaza City.â€ | G205: 0 | H205: 0 | I205: 1 | J205: 0 | K205: 1 | L205: 0 | M205: 0 | N205: 0 | O205: 0 | P205: 12 | Q205: 355 | R205: 0.149 | S205: 0.114 | T205: 0.34 | U205: 0.436 | V205: 0.5 | W205: 0.414 | X205: 0.138 | Y205: 0.5 | Z205: 0.126 | AA205: 0.5 | AB205: 0.5 | AC205: 0.1315 | AD205: Title: As Gaza War Enters New Phase, Israel Faces Pressure Over Civilian Deaths. Title: As Gaza War Enters New Phase, Israel Faces Pressure Over Civilian Deaths. First Paragraph: Fears are rising that the conflict could spread to the occupied West Bank, where tensions are soaring among Palestinians angered over deadly Israeli airstrikes in Gaza. Nearly a week after Israeli tanks and troops poured into Gaza, Israeli military officials say they have made steady gains against Hamas. But the ground operation, which now encircles Gaza City, is entering an acutely perilous phase, with Israeli troops advancing in an urban landscape that is honeycombed with tunnels and home to many Palestinians. Israeli airstrikes this week on a densely populated neighborhood in northern Gaza that have killed scores of civilians are fueling fears that the war could spread to a second front: the much larger occupied West Bank, where Palestinians have been enraged by the bombardment, which has killed thousands. Harrowing images of the dead and wounded are also intensifying international pressure on Israel. On Friday, Secretary of State Antony J. Blinken pressed Prime Minister Benjamin Netanyahu to order â€œhumanitarian pausesâ€ in the operation to allow more aid to reach civilians and more people to leave the strip. But Mr. Netanyahu later appeared to reject the idea of pausing the military campaign, saying that any cease-fire would depend on the freeing of Israeli hostages held by Hamas in Gaza. One senior Israeli military official said he was confident that the troops would seize control of Gaza, and Israel claims to have killed hundreds of Hamas militants in its assaults. But the official was not sure, with global public opinion turning sharply against Israel, that they would have enough time to root out all of the Hamas forces â€” a push that Israeli leaders have said could take months. Publicly, Israeli commanders are claiming steady gains, but offering few details, about their military response to the Hamas attacks of Oct. 7, which left 1,400 soldiers and civilians dead, including women, children and older people and which included torture and abuse. â€œOur forces are at the heart of a ground operation in the north of the Gaza Strip,â€ Lt. Gen. Herzi Halevi, the Israeli military chief of staff, said in a statement on Thursday. â€œWeâ€™re encircling Gaza City.â€ | AE205: 45233 | AF205: 45233 | AG205: 2023 | AH205: israeli | AI205: gaza | AJ205: israel
A206: 205 | B206: 45233 | C206: Isaac Herzog | D206: The New York Times | E206: The President of Israel: This Is Not a Battle Just Between Israel and Hamas | F206: I write these lines from Jerusalem, after spending time with the families of some of the 240 people kidnapped by Hamas terrorists on Oct. 7. The hostages now held in Gaza include Jewish Israelis, Muslim Israelis and foreign citizens of different ethnicities. In all my years of public life, the meetings with these families were the most difficult and fraught Iâ€™ve ever held. Iâ€™ve also spoken with families of some of the more than 1,400 of my people who were killed that day, many of them murdered in their living rooms and kitchens or dancing at a music festival. When I returned from one kibbutz devastated in the attack, I had to wash the blood off my shoes. Tragedy is part of Israeli life, and I knew it would be part of my time as president. But none of us imagined a tragedy like this. Against our will, we in Israel find ourselves at a tipping point for the Middle East and for the world and at the center of what is nothing less than an existential struggle. This is not a battle between Jews and Muslims. And it is not just between Israel and Hamas. It is between those who adhere to norms of humanity and those practicing a barbarism that has no place in the modern world. Just like ISIS and Al Qaeda, the Hamas terrorists who attacked Israeli homes and families had no qualms about burning babies. They tortured children, raped women and destroyed peace-loving communities. They were so proud of their deeds that they made sure to capture them on video and even broadcast them live. These videos will forever remain a stain on those Palestinians and their supporters who celebrated that day and a testament to the depravity of the terrorists and of the ideas that inspired them. But almost as disturbing for me is the realization that many in the world, including in the West, are willing to rationalize these actions or even support them outright. In the capitals of Europe weâ€™ve seen rallies supporting the total destruction of Israel â€œfrom the river to the sea.â€ Professors and students at American colleges make speeches and sign statements justifying terrorism, even glorifying it. Weâ€™ve heard certain governments fail to denounce Hamas, instead condemning Israelâ€™s response and even seeking to offer justification for Hamasâ€™s atrocities. It would have been unthinkable to hear such moral confusion uttered after the Sept. 11 attacks or after bombings in London, Barcelona and Baghdad. When I spoke to a joint meeting of Congress this year, I said terrorism â€œcontradicts humanityâ€™s most basic principles of peace.â€ It turns out that not everyone agrees. All of this shows that this collision of values is happening not just here in Israel but everywhere and that the terrorist ideology threatens all decent people, not only Jews. History has taught us that foul ideologies often find the Jewish people first â€” but tend not to stop there. We find ourselves on the front lines of this battle, but all nations face this threat, and they must understand that they could be next. Since Hamas forced this war on us, our military has been acting to permanently eliminate this unbearable threat and to enable the return of our hostages. This means fighting in the battlefield that Hamas has created in Gaza over many years â€” one in which terrorists hide behind and within the civilian population. This is a battlefield with terrorist tunnels under civilian streets, one in which civilian casualties are not avoided at all costs but rather encouraged by Hamas in order to draw global sympathy and blunt Israelâ€™s response. Not only does Hamas store rockets under schools and homes; our intelligence and the confessions of captured terrorists show that the Hamas command center is hidden under Gazaâ€™s central hospital. The result of these sickening tactics is the civilian suffering we are all watching unfold. Many reports of the humanitarian difficulties in parts of Gaza are unverifiable, but there is real suffering, and it concerns us, too. These are our neighbors, and our full withdrawal from Gaza in 2005 was meant to give them free lives and open the door for peace. To our dismay, Hamas and its many Palestinian supporters chose otherwise. Even as Hamas fires hundreds of rockets at our cities and as our soldiers fall in battle, weâ€™re making an effort to give early warning to civilians with leaflets and phone calls, to move them out of the main battle zones and to enable humanitarian aid through Gazaâ€™s border with Egypt. Hundreds of aid trucks are now arriving, with more expected each day. But anyone who thinks the cynical exploitation of civilian suffering will tie our hands and save Hamas this time is wrong. For us and for the Palestinians, the suffering will end only with the removal of Hamas. Anyone trying to tie our hands is, intentionally or not, undermining not only Israelâ€™s defense but also any hope for a world where these atrocities cannot happen. In the months and years before the Hamas massacre, we began to see signs of the emergence of a better Middle East, from the Persian Gulf to North Africa â€” one inspired by progress and partnership, one in which Israel could finally feel at home among our neighbors. Will this be the world that emerges from this crisis? Or will it be the world desired by the murderous fundamentalists of Hamas? These questions will be key among the strategic issues on the agenda in our discussions with Secretary of State Antony Blinken during his visit to the region beginning Friday â€” as they were during the visit to Israel of President Biden a few weeks ago. Much is at stake at this moment, not just the future of Israel. On Oct. 7 we were all jolted awake and presented with a shocking challenge to our hopes and morals. How we meet this challenge will shape our future. | G206: 0 | H206: 1 | I206: 0 | J206: 0 | K206: 0 | L206: 1 | M206: 1 | N206: 0 | O206: 0 | P206: 14 | Q206: 992 | R206: 0.431 | S206: 0.21 | T206: 0.522 | U206: 0.5 | V206: 0.5 | W206: 0.173 | X206: 0.079 | Y206: 0.095 | Z206: 0.176 | AA206: 0.5 | AB206: 0.5 | AC206: 0.3205 | AD206: Title: The President of Israel: This Is Not a Battle Just Between Israel and Hamas. Title: The President of Israel: This Is Not a Battle Just Between Israel and Hamas. First Paragraph: I write these lines from Jerusalem, after spending time with the families of some of the 240 people kidnapped by Hamas terrorists on Oct. 7. The hostages now held in Gaza include Jewish Israelis, Muslim Israelis and foreign citizens of different ethnicities. In all my years of public life, the meetings with these families were the most difficult and fraught Iâ€™ve ever held. Iâ€™ve also spoken with families of some of the more than 1,400 of my people who were killed that day, many of them murdered in their living rooms and kitchens or dancing at a music festival. When I returned from one kibbutz devastated in the attack, I had to wash the blood off my shoes. Tragedy is part of Israeli life, and I knew it would be part of my time as president. But none of us imagined a tragedy like this. Against our will, we in Israel find ourselves at a tipping point for the Middle East and for the world and at the center of what is nothing less than an existential struggle. This is not a battle between Jews and Muslims. And it is not just between Israel and Hamas. It is between those who adhere to norms of humanity and those practicing a barbarism that has no place in the modern world. Just like ISIS and Al Qaeda, the Hamas terrorists who attacked Israeli homes and families had no qualms about burning babies. They tortured children, raped women and destroyed peace-loving communities. They were so proud of their deeds that they made sure to capture them on video and even broadcast them live. These videos will forever remain a stain on those Palestinians and their supporters who celebrated that day and a testament to the depravity of the terrorists and of the ideas that inspired them. But almost as disturbing for me is the realization that many in the world, including in the West, are willing to rationalize these actions or even support them outright. In the capitals of Europe weâ€™ve seen rallies supporting the total destruction of Israel â€œfrom the river to the sea.â€ Professors and students at American colleges make speeches and sign statements justifying terrorism, even glorifying it. Weâ€™ve heard certain governments fail to denounce Hamas, instead condemning Israelâ€™s response and even seeking to offer justification for Hamasâ€™s atrocities. It would have been unthinkable to hear such moral confusion uttered after the Sept. 11 attacks or after bombings in London, Barcelona and Baghdad. When I spoke to a joint meeting of Congress this year, I said terrorism â€œcontradicts humanityâ€™s most basic principles of peace.â€ It turns out that not everyone agrees. All of this shows that this collision of values is happening not just here in Israel but everywhere and that the terrorist ideology threatens all decent people, not only Jews. History has taught us that foul ideologies often find the Jewish people first â€” but tend not to stop there. We find ourselves on the front lines of this battle, but all nations face this threat, and they must understand that they could be next. Since Hamas forced this war on us, our military has been acting to permanently eliminate this unbearable threat and to enable the return of our hostages. This means fighting in the battlefield that Hamas has created in Gaza over many years â€” one in which terrorists hide behind and within the civilian population. This is a battlefield with terrorist tunnels under civilian streets, one in which civilian casualties are not avoided at all costs but rather encouraged by Hamas in order to draw global sympathy and blunt Israelâ€™s response. Not only does Hamas store rockets under schools and homes; our intelligence and the confessions of captured terrorists show that the Hamas command center is hidden under Gazaâ€™s central hospital. The result of these sickening tactics is the civilian suffering we are all watching unfold. Many reports of the humanitarian difficulties in parts of Gaza are unverifiable, but there is real suffering, and it concerns us, too. These are our neighbors, and our full withdrawal from Gaza in 2005 was meant to give them free lives and open the door for peace. To our dismay, Hamas and its many Palestinian supporters chose otherwise. Even as Hamas fires hundreds of rockets at our cities and as our soldiers fall in battle, weâ€™re making an effort to give early warning to civilians with leaflets and phone calls, to move them out of the main battle zones and to enable humanitarian aid through Gazaâ€™s border with Egypt. Hundreds of aid trucks are now arriving, with more expected each day. But anyone who thinks the cynical exploitation of civilian suffering will tie our hands and save Hamas this time is wrong. For us and for the Palestinians, the suffering will end only with the removal of Hamas. Anyone trying to tie our hands is, intentionally or not, undermining not only Israelâ€™s defense but also any hope for a world where these atrocities cannot happen. In the months and years before the Hamas massacre, we began to see signs of the emergence of a better Middle East, from the Persian Gulf to North Africa â€” one inspired by progress and partnership, one in which Israel could finally feel at home among our neighbors. Will this be the world that emerges from this crisis? Or will it be the world desired by the murderous fundamentalists of Hamas? These questions will be key among the strategic issues on the agenda in our discussions with Secretary of State Antony Blinken during his visit to the region beginning Friday â€” as they were during the visit to Israel of President Biden a few weeks ago. Much is at stake at this moment, not just the future of Israel. On Oct. 7 we were all jolted awake and presented with a shocking challenge to our hopes and morals. How we meet this challenge will shape our future. | AE206: 45233 | AF206: 45233 | AG206: 2023 | AH206: hamas | AI206: battle | AJ206: israel
A207: 206 | B207: 45233 | C207: Aaron Boxerman | D207: The New York Times | E207: The U.N. says it needs four times as much money for aid efforts for Palestinians. | F207: The United Nations said on Friday that it needed $1.2 billion to fund humanitarian efforts for Palestinians through the end of the year â€” more than four times what it asked for just weeks ago â€” as conditions for civilians worsen rapidly in Gaza and the occupied West Bank. After nearly a month of intense Israeli bombardment that has displaced more than a million people and destroyed large areas of housing in Gaza, â€œthe situation has grown increasingly desperate,â€ said Jens Laerke, a spokesman for the U.N. humanitarian office. The $1.2 billion appeal announced on Friday is for 2.7 million Palestinians in Gaza and the West Bank. The United Nations had received only a quarter of the $294 million that it requested in mid-October, Mr. Laerke said, with the biggest external contributions coming from the United States ($24.5 million) and Japan ($7 million). More than 370 trucks carrying humanitarian aid and relief supplies have crossed into Gaza through the Rafah gate on the Egyptian border since Oct. 21, amid mounting pressure on Israel from the United States and other allies to increase the flow of food, water, medicine and other essential items to Gaza civilians. But U.N. officials now say that hundreds of trucks are needed daily to meet the needs of Gazaâ€™s population. To enable a scaling-up of aid flows to Gaza, U.N. officials have also called for the reopening of border crossings from Israel into Gaza, including at Kerem Shalom. Some U.N. officials and diplomats have blamed Israeli security checks for the delays, but Col. Elad Goren, a senior Israeli military officer, said in an interview that Israeli officials were ready to facilitate inspections of many more truckloads at Nitzana, a border post about 25 miles from Rafah. â€œIsrael will not be the bottleneck,â€ Colonel Goren said, adding that the issue was â€œthe capacity of international organizations to absorb the aid via Rafah.â€ The colonel serves in COGAT, Israelâ€™s agency overseeing policy for the Palestinian territories. Israel, which, along with Egypt, maintains a blockade of Gaza, has denied that there is a humanitarian crisis in the territory and has refused to agree to let fuel shipments in through Rafah, arguing that it could be used by Hamas. But on Thursday, the Israeli militaryâ€™s chief of staff, Lt. Gen. Herzi Halevi, indicated that Israeli policy could change. And Colonel Goren said in the interview that COGAT was beginning to discuss ways of distributing fuel to ensure that it does not go to Hamas, if Israeli political leaders approve allowing it into Gaza. Israeli officials would track the fuel â€œfrom above, and the United Nations would be required to give us information so that we could see that it reached the places that we authorized,â€ Colonel Goren said. | G207: 0 | H207: 0 | I207: 1 | J207: 0 | K207: 0 | L207: 0 | M207: 0 | N207: 0 | O207: 0 | P207: 15 | Q207: 458 | R207: 0.357 | S207: 0.292 | T207: 0.367 | U207: 0.5 | V207: 0.5 | W207: 0.141 | X207: 0.546 | Y207: 0.558 | Z207: 0.307 | AA207: 0.5 | AB207: 0.5 | AC207: 0.3245 | AD207: Title: The U.N. says it needs four times as much money for aid efforts for Palestinians.. Title: The U.N. says it needs four times as much money for aid efforts for Palestinians.. First Paragraph: The United Nations said on Friday that it needed $1.2 billion to fund humanitarian efforts for Palestinians through the end of the year â€” more than four times what it asked for just weeks ago â€” as conditions for civilians worsen rapidly in Gaza and the occupied West Bank. After nearly a month of intense Israeli bombardment that has displaced more than a million people and destroyed large areas of housing in Gaza, â€œthe situation has grown increasingly desperate,â€ said Jens Laerke, a spokesman for the U.N. humanitarian office. The $1.2 billion appeal announced on Friday is for 2.7 million Palestinians in Gaza and the West Bank. The United Nations had received only a quarter of the $294 million that it requested in mid-October, Mr. Laerke said, with the biggest external contributions coming from the United States ($24.5 million) and Japan ($7 million). More than 370 trucks carrying humanitarian aid and relief supplies have crossed into Gaza through the Rafah gate on the Egyptian border since Oct. 21, amid mounting pressure on Israel from the United States and other allies to increase the flow of food, water, medicine and other essential items to Gaza civilians. But U.N. officials now say that hundreds of trucks are needed daily to meet the needs of Gazaâ€™s population. To enable a scaling-up of aid flows to Gaza, U.N. officials have also called for the reopening of border crossings from Israel into Gaza, including at Kerem Shalom. Some U.N. officials and diplomats have blamed Israeli security checks for the delays, but Col. Elad Goren, a senior Israeli military officer, said in an interview that Israeli officials were ready to facilitate inspections of many more truckloads at Nitzana, a border post about 25 miles from Rafah. â€œIsrael will not be the bottleneck,â€ Colonel Goren said, adding that the issue was â€œthe capacity of international organizations to absorb the aid via Rafah.â€ The colonel serves in COGAT, Israelâ€™s agency overseeing policy for the Palestinian territories. Israel, which, along with Egypt, maintains a blockade of Gaza, has denied that there is a humanitarian crisis in the territory and has refused to agree to let fuel shipments in through Rafah, arguing that it could be used by Hamas. But on Thursday, the Israeli militaryâ€™s chief of staff, Lt. Gen. Herzi Halevi, indicated that Israeli policy could change. And Colonel Goren said in the interview that COGAT was beginning to discuss ways of distributing fuel to ensure that it does not go to Hamas, if Israeli political leaders approve allowing it into Gaza. Israeli officials would track the fuel â€œfrom above, and the United Nations would be required to give us information so that we could see that it reached the places that we authorized,â€ Colonel Goren said. | AE207: 45233 | AF207: 45233 | AG207: 2023 | AH207: israeli | AI207: israel | AJ207: gaza
A208: 207 | B208: 45232 | C208: Isabel Kershner | D208: The New York Times | E208: A Hamas official vows more attacks against Israel. | F208: Even as Israeli warplanes pounded Gaza last week ahead of a major ground invasion, Ghazi Hamad, a member of Hamasâ€™s political bureau, unabashedly championed the Oct. 7 terror attack Hamas launched from Gaza that prompted those airstrikes. And he promised similar future assaults with the goal of annihilating Israel. The surprise attack of Oct. 7 â€œwas just the first time, and there will be a second, a third, a fourth,â€ he told a Lebanese television channel in an interview that aired on Oct. 24 and was later put online by a media watchdog organization. â€œWe must teach Israel a lesson, and we will do this again and again,â€ Mr. Hamad said in the interview, according to clips of the interview published and translated by the Middle East Media Research Institute, or MEMRI, a nonprofit monitoring group founded by an Israeli and an Israeli-American that is based in Washington, D.C. The videos, as they appeared on the groupâ€™s website, had been edited for length but the provided translations were accurate. At least 1,400 people, mostly Israeli civilians, were killed in the Hamas assault, according to Israeli officials, making Oct. 7 the deadliest day in Israelâ€™s 75-year history. Assailants abducted more than 240 hostages, among them grandparents and children, including a 9-month-old baby. Since then, more than 9,000 people in Gaza have been killed, according to health officials in the Hamas-run Palestinian enclave, in the Israeli airstrikes and ground operations that the government says are aimed at rooting out Hamasâ€™s infrastructure. Mr. Hamad asserted that his group had not wanted to harm civilians on Oct. 7 but ran into complications on the ground. His comment was at odds with instructions the assailants had received, according to documents they left behind that were gathered by the Israeli military. Many of the assailants also filmed themselves killing civilians and perpetrating atrocities, uploading the images to social media in real time. He said that Palestinians were willing to pay the price. â€œWe are called a nation of martyrs,â€ he said, â€œand we are proud to sacrifice martyrs.â€ He presented the Palestinians as â€œthe victims of the occupation. Period.â€ When asked by the interviewer if he meant the occupation of Gaza, he replied, â€œNo, I am talking about all the Palestinian lands.â€ Asked if that meant the annihilation of Israel, he said, â€œYes, of course,â€ adding that Israelâ€™s existence was â€œillogical.â€ â€œNobody should blame us for the things we do,â€ he said, adding, â€œOctober 7th, October 10th, the millionth of October â€” everything we do is justified,â€ repeating the word justified in English for emphasis. In an interview two days later with The Associated Press in Beirut, Mr. Hamad said that Hamas expected more support from its allies in the region, including the Iranian-backed Hezbollah organization in Lebanon. | G208: 0 | H208: 0 | I208: 1 | J208: 0 | K208: 1 | L208: 0 | M208: 0 | N208: 0 | O208: 0 | P208: 8 | Q208: 462 | R208: 0.079 | S208: 0.271 | T208: 0.459 | U208: 0.5 | V208: 0.5 | W208: 0.113 | X208: 0.173 | Y208: 0.147 | Z208: 0.127 | AA208: 0.5 | AB208: 0.5 | AC208: 0.175 | AD208: Title: A Hamas official vows more attacks against Israel.. Title: A Hamas official vows more attacks against Israel.. First Paragraph: Even as Israeli warplanes pounded Gaza last week ahead of a major ground invasion, Ghazi Hamad, a member of Hamasâ€™s political bureau, unabashedly championed the Oct. 7 terror attack Hamas launched from Gaza that prompted those airstrikes. And he promised similar future assaults with the goal of annihilating Israel. The surprise attack of Oct. 7 â€œwas just the first time, and there will be a second, a third, a fourth,â€ he told a Lebanese television channel in an interview that aired on Oct. 24 and was later put online by a media watchdog organization. â€œWe must teach Israel a lesson, and we will do this again and again,â€ Mr. Hamad said in the interview, according to clips of the interview published and translated by the Middle East Media Research Institute, or MEMRI, a nonprofit monitoring group founded by an Israeli and an Israeli-American that is based in Washington, D.C. The videos, as they appeared on the groupâ€™s website, had been edited for length but the provided translations were accurate. At least 1,400 people, mostly Israeli civilians, were killed in the Hamas assault, according to Israeli officials, making Oct. 7 the deadliest day in Israelâ€™s 75-year history. Assailants abducted more than 240 hostages, among them grandparents and children, including a 9-month-old baby. Since then, more than 9,000 people in Gaza have been killed, according to health officials in the Hamas-run Palestinian enclave, in the Israeli airstrikes and ground operations that the government says are aimed at rooting out Hamasâ€™s infrastructure. Mr. Hamad asserted that his group had not wanted to harm civilians on Oct. 7 but ran into complications on the ground. His comment was at odds with instructions the assailants had received, according to documents they left behind that were gathered by the Israeli military. Many of the assailants also filmed themselves killing civilians and perpetrating atrocities, uploading the images to social media in real time. He said that Palestinians were willing to pay the price. â€œWe are called a nation of martyrs,â€ he said, â€œand we are proud to sacrifice martyrs.â€ He presented the Palestinians as â€œthe victims of the occupation. Period.â€ When asked by the interviewer if he meant the occupation of Gaza, he replied, â€œNo, I am talking about all the Palestinian lands.â€ Asked if that meant the annihilation of Israel, he said, â€œYes, of course,â€ adding that Israelâ€™s existence was â€œillogical.â€ â€œNobody should blame us for the things we do,â€ he said, adding, â€œOctober 7th, October 10th, the millionth of October â€” everything we do is justified,â€ repeating the word justified in English for emphasis. In an interview two days later with The Associated Press in Beirut, Mr. Hamad said that Hamas expected more support from its allies in the region, including the Iranian-backed Hezbollah organization in Lebanon. | AE208: 45232 | AF208: 45232 | AG208: 2023 | AH208: israeli | AI208: israel | AJ208: gaza
A209: 208 | B209: 45232 | C209: Matthew Mpoke Bigg | D209: The New York Times | E209: Israel rejects the U.N. human rights agencyâ€™s concern that Israeli strikes on Jabaliya may constitute war crimes. | F209: The United Nations human rights agency expressed â€œserious concernsâ€ on Wednesday that the casualties and destruction caused by Israeli airstrikes this week on Gazaâ€™s Jabaliya neighborhood, near Gaza City, could amount to war crimes. Israel responded on Thursday, saying that it operated under the laws of war. A spokesman for Israelâ€™s Ministry of Foreign Affairs, Lior Haiat, accused Hamas of using Gazans as human shields. He said that â€œthe entire responsibility lies on the terrorists of Hamas.â€ â€œNo other country in the world is making the same effort as Israel to prevent civilian casualties,â€ Mr. Haiat said. Emergency workers were picking through the rubble in Jabaliya on Thursday, two days after missile strikes decimated the densely packed neighborhood of apartment blocks and houses. The health ministry in Gaza said that more than 1,000 people had been injured, killed or were missing after strikes on Tuesday and Wednesday. On Thursday, Jabaliya was hit again. The U.N. Human Rights Office said in a post on social media on Wednesday that â€œwe have serious concerns that these are disproportionate attacks that could amount to war crimes.â€ Israelâ€™s military said that it had killed a commander for Hamas and destroyed tunnels built by the group in its airstrikes on Tuesday.The strikes came in a war set off when Hamas staged an incursion into Israel on Oct. 7, killing 1,400 civilians and soldiers. It also took more than 200 people hostage, according to the Israeli government, of which a handful have been released or rescued. The attacks were launched from Gaza, which Hamas controls and where its fighters are embedded among the civilian population. Mr. Haiat, in his comments responding to the U.N. criticism, said that Israel was fighting a terrorist organization that â€œis worse than ISIS,â€ referring to the Islamic State. The Islamic State, which ruled territory in Iraq and Syria between 2014 and 2019 and has spawned offshoots elsewhere, sought to pursue global Islamic rule through battle with anyone who opposed their ideology, including other Muslims. Hamas is a Palestinian organization committed solely to the destruction of Israel. Hamasâ€™s fighters, command posts and other infrastructure are scattered among Gazaâ€™s communities, and Israel has contended that it is impossible to strike Hamas without also hurting noncombatants. But some human rights groups have criticized Israelâ€™s airstrikes and siege of the enclave as disproportionate, and there have been growing calls for a humanitarian pause. Israeli forces have launched thousands of strikes in Gaza since Oct. 7 and last Friday began an invasion of the territory to crush the group. Health authorities in Gaza, a territory of around 2.3 million people, say that more than 8,700 people have been killed, including more than 3,600 children. The health ministry does not say how many Hamas personnel or fighters are included in its figures. Israel has also expanded its 16-year blockade of Gaza, cutting off supplies of water, fuel and food to the territory. The U.N. Human Rights Officeâ€™s comments on Wednesday were not the first time since Oct. 7 that it has spoken of war crimes in relation to the conflict. Last week, a spokeswoman, Ravina Shamdasani, told a news briefing that indiscriminate attacks by Palestinian armed groups, including rocket attacks on Israel, must stop and that the taking of hostages was a war crime. But she also said that Israelâ€™s call for civilians in Gaza to move from the north to the south of the enclave raised serious concerns about whether they were being forcibly transferred, which is a war crime. And she said that â€œIsraelâ€™s collective punishment of the entire population must immediately cease,â€ calling that a war crime. The Israeli prime minister, Benjamin Netanyahu, has dismissed accusations that Israel is inflicting collective punishment on the civilian population. The director of the U.N. Human Rights agencyâ€™s New York office resigned this week, accusing the United Nations of abandoning its own principles and international law over Gaza, and of failing to stop Israelâ€™s bombardment, which he characterized as â€œgenocide.â€ A spokeswoman for the agency said that the director, Craig Mokhiber, had expressed a personal view. | G209: 1 | H209: 0 | I209: 1 | J209: 0 | K209: 1 | L209: 0 | M209: 0 | N209: 1 | O209: 1 | P209: 17 | Q209: 678 | R209: 0.093 | S209: 0.122 | T209: 0.134 | U209: 0.412 | V209: 0.5 | W209: 0.113 | X209: 0.173 | Y209: 0.061 | Z209: 0.091 | AA209: 0.5 | AB209: 0.5 | AC209: 0.1075 | AD209: Title: Israel rejects the U.N. human rights agencyâ€™s concern that Israeli strikes on Jabaliya may constitute war crimes.. Title: Israel rejects the U.N. human rights agencyâ€™s concern that Israeli strikes on Jabaliya may constitute war crimes.. First Paragraph: The United Nations human rights agency expressed â€œserious concernsâ€ on Wednesday that the casualties and destruction caused by Israeli airstrikes this week on Gazaâ€™s Jabaliya neighborhood, near Gaza City, could amount to war crimes. Israel responded on Thursday, saying that it operated under the laws of war. A spokesman for Israelâ€™s Ministry of Foreign Affairs, Lior Haiat, accused Hamas of using Gazans as human shields. He said that â€œthe entire responsibility lies on the terrorists of Hamas.â€ â€œNo other country in the world is making the same effort as Israel to prevent civilian casualties,â€ Mr. Haiat said. Emergency workers were picking through the rubble in Jabaliya on Thursday, two days after missile strikes decimated the densely packed neighborhood of apartment blocks and houses. The health ministry in Gaza said that more than 1,000 people had been injured, killed or were missing after strikes on Tuesday and Wednesday. On Thursday, Jabaliya was hit again. The U.N. Human Rights Office said in a post on social media on Wednesday that â€œwe have serious concerns that these are disproportionate attacks that could amount to war crimes.â€ Israelâ€™s military said that it had killed a commander for Hamas and destroyed tunnels built by the group in its airstrikes on Tuesday.The strikes came in a war set off when Hamas staged an incursion into Israel on Oct. 7, killing 1,400 civilians and soldiers. It also took more than 200 people hostage, according to the Israeli government, of which a handful have been released or rescued. The attacks were launched from Gaza, which Hamas controls and where its fighters are embedded among the civilian population. Mr. Haiat, in his comments responding to the U.N. criticism, said that Israel was fighting a terrorist organization that â€œis worse than ISIS,â€ referring to the Islamic State. The Islamic State, which ruled territory in Iraq and Syria between 2014 and 2019 and has spawned offshoots elsewhere, sought to pursue global Islamic rule through battle with anyone who opposed their ideology, including other Muslims. Hamas is a Palestinian organization committed solely to the destruction of Israel. Hamasâ€™s fighters, command posts and other infrastructure are scattered among Gazaâ€™s communities, and Israel has contended that it is impossible to strike Hamas without also hurting noncombatants. But some human rights groups have criticized Israelâ€™s airstrikes and siege of the enclave as disproportionate, and there have been growing calls for a humanitarian pause. Israeli forces have launched thousands of strikes in Gaza since Oct. 7 and last Friday began an invasion of the territory to crush the group. Health authorities in Gaza, a territory of around 2.3 million people, say that more than 8,700 people have been killed, including more than 3,600 children. The health ministry does not say how many Hamas personnel or fighters are included in its figures. Israel has also expanded its 16-year blockade of Gaza, cutting off supplies of water, fuel and food to the territory. The U.N. Human Rights Officeâ€™s comments on Wednesday were not the first time since Oct. 7 that it has spoken of war crimes in relation to the conflict. Last week, a spokeswoman, Ravina Shamdasani, told a news briefing that indiscriminate attacks by Palestinian armed groups, including rocket attacks on Israel, must stop and that the taking of hostages was a war crime. But she also said that Israelâ€™s call for civilians in Gaza to move from the north to the south of the enclave raised serious concerns about whether they were being forcibly transferred, which is a war crime. And she said that â€œIsraelâ€™s collective punishment of the entire population must immediately cease,â€ calling that a war crime. The Israeli prime minister, Benjamin Netanyahu, has dismissed accusations that Israel is inflicting collective punishment on the civilian population. The director of the U.N. Human Rights agencyâ€™s New York office resigned this week, accusing the United Nations of abandoning its own principles and international law over Gaza, and of failing to stop Israelâ€™s bombardment, which he characterized as â€œgenocide.â€ A spokeswoman for the agency said that the director, Craig Mokhiber, had expressed a personal view. | AE209: 45232 | AF209: 45232 | AG209: 2023 | AH209: israel | AI209: human rights | AJ209: war crimes
A210: 209 | B210: 45232 | C210: Thomas Friedman | D210: The New York Times | E210: The Two Things Worrying U.S. Military Officials About Israel and Hamas | F210: Step back far enough, and you can see exactly what is driving so much geopolitics today: Ukraine is trying to join the West. Israel is trying to join a new Middle East. And Russia and Iran have teamed up to try to block both. Unfortunately, the new G.O.P. House speaker, Mike Johnson, is either too inexperienced or too ideological (or both) to see this (or to care). He is pushing a budget that would help Israel better defend itself but would deprive Ukraine of essential U.S. economic and military assistance to beat back Russiaâ€™s onslaught. And heâ€™s conditioned even the $14.3 billion the administration wants to send to Israel on President Biden agreeing to strip the same amount from funds added for the Internal Revenue Service so it could better collect taxes from cheaters. (Attention, Israel lobby: Do not go along with that game. Next time, aid for Israel will be tied to extreme G.O.P. positions on abortion or guns.) Thank goodness Johnson was not the speaker during World War II; he and his myopic members might have pressed to fund the war against the Germans in Europe but not against the Japanese in the Pacific. Or they would have agreed to Lend-Lease assistance for the allies only if President Franklin Roosevelt would eliminate the I.R.S. altogether. More guns, more butter, no taxes and two fronts. If it sounds like an utterly incoherent worldview that would undermine the American global leadership that has shaped a world weâ€™ve thrived in for the past century, itâ€™s because it is. And if it feels as if House G.O.P. leaders are small thinkers in a big time, itâ€™s because they are. They are shameless, shameful and dangerous. Please do our country a favor and audition for Fox News on some other issue. Because this IS a big moment â€” comparable to 1945 or 1989. If Ukraine is able to escape Russiaâ€™s grasp and eventually join NATO and the European Union â€” with its formidable army, agricultural exports and technology prowess â€” it would be a giant boost for a Europe whole and free. And if Israel can be maneuvered back to the bargaining table for a two-state solution with the Palestinian Authority â€” to pave the way for normalization between the Jewish state and Saudi Arabia â€” it would be a huge boost for a new, more pluralistic Middle East built around Palestinians, other Arabs and Israelis focused on strengthening their peopleâ€™s resilience for the future and not their resistance to each other and to the West. If these tectonic shifts can happen, the post-post-Cold War world has a far greater chance to handle other global challenges, like climate change, than if these shifts are stymied. But you donâ€™t need to speak Arabic, Hebrew, Persian, Russian or Ukrainian to understand that Iran-backed Hamas launched its war to stymie the Saudi-Israel normalization and prevent Tehran from being isolated, and that Vladimir Putin launched his war to stop Ukraine from expanding a Europe whole and free and prevent Moscow from being isolated. Russia under Putin and Iran under its supreme leader, Ayatollah Ali Khamenei, have a lot in common, argued the Russia expert Leon Aron, the author of â€œRiding the Tiger: Vladimir Putinâ€™s Russia and the Uses of War.â€ â€œBoth leaders have nothing to offer their people other than quasi-religious wars which enable them to stay in power by keeping their countries either at war or primed for war,â€ he told me. And both leaders are gunning for other countries whose aspirations are the antithesis of Russiaâ€™s and Iranâ€™s poisonous core regime identities. â€œUkraine proves that there can be a Slavic, Orthodox country, very close to Russia ethnically â€” yet free, democratic and thriving, with a Western political and economic orientation and not needing a state of war with the West or to be a police state like Belarus or a military dictatorship like Russia,â€ Aron said. Meanwhile, normalization of relations between the Jewish state and Saudi Arabia, the birthplace of Islam, would very likely pave the way for normalization between Israel and the most populous Muslim country in the world, Indonesia, as well as Malaysia and maybe later even Pakistan. It would prove that Jews and Muslims arenâ€™t destined to be forever in conflict and can revive the not always harmonious â€” but often harmonious â€” relations their communities enjoyed throughout much of history before the Palestinian conflict. As I said, nothing would have isolated Iran more. And Hamas knew that if Israel was able to normalize with Saudi Arabia on terms that would satisfy the more moderate Palestinian Authority in the West Bank and bring it significant financial advantages and more legitimacy, the Hamas Gaza resistance-forever model would have been totally isolated. So Hamas launched this war knowing it would bring death and ruin not only to many Israelis but also to many more of its own innocent civilians. Disgusting. Iran knew the same. All of this has created a huge opportunity for Putin. He welcomed a Hamas delegation to Moscow last week, and he has an expanding relationship with Iran underway; Iran is supplying Putin with drones and missiles to kill Ukrainians, in return for cybertechnologies, advanced aircraft and possibly antiaircraft equipment for Tehran. Itâ€™s a win-win-win for Putin. By helping Iran fuel the flames of a war between Israel and Iranâ€™s Middle East proxies, Putin knows he is forcing the U.S. to send more spare parts, Patriot missiles and 155-millimeter artillery shells to Israel instead of to Ukraine. And if that flow of arms to Kyiv is then cut off by Johnson and the House G.O.P., all Putin needs to do is count the days until Donald Trump is re-elected and Ukraine is his â€” or so he probably assumes. Plus all the instability drives up oil prices! While Republicans play dangerous games with military and economic aid, here are the two things that U.S. military officials tell me they are worried about: They believe that the Israelis want to take just Gaza City, where the core of Hamas military and manpower infrastructure is, and then use that as a launching pad for more tactical attacks on Hamasâ€™s leadership and rocket launchers in the rest of Gaza â€” without occupying it all. But Israelâ€™s military advance is already encountering a common challenge in urban warfare: You get stalled in the alleyways and then call in air power to blow away the enemy and anyone else nearby, leading to significant civilian casualties. The U.S. cannot ignore or defend that strategy for much longer, U.S. officials say. Second, the U.S. still sees a giant hole in the heart of Israelâ€™s strategy: Who will govern Gaza if and when Hamas is evicted? The only likely possibility is the Palestinian Authority in Ramallah, in the West Bank. But the only way those Palestinian leaders will assume that role is if Israel permits their capabilities to grow â€” provided they get their act together â€” and if Israel is seen as advancing a two-state solution. But the current government of Benjamin Netanyahu is dedicated to annexing the West Bank. So it looks as if Israelâ€™s army is reoccupying Gaza to eventually turn it over to some kind of legitimate Palestinian Authority â€” while Israelâ€™s extreme right-wing politicians and settlers are working overtime to delegitimize that authority and drive Palestinians out of the West Bank. This is a strategic contradiction. Israel actually needs a wartime peace process with the Palestinian Authority. The cold hard truth is this: Israel cannot get out of Gaza and sustain Western support without a credible Palestinian partner to govern there, and Ukraine cannot sustain Western support unless it makes substantial gains against Putinâ€™s army this winter or decides thatâ€™s impossible and agrees to some kind of dirty deal. That is, some kind of territorial compromise with Putin in return for a NATO security guarantee and a pathway to the European Union. No Western leaders are ready to say that out loud to Kyiv, but they all know it and believe it: Western support for Ukraine cannot and will not be there for an endless war of attrition. Thatâ€™s why today America must help Israel and Ukraine to blunt the Russia-Iran axis in their theaters. But the morning after their wars, Israel and Ukraine are going to have to face some very hard choices. Because while we may write big checks to both, they will not be blank checks. Each will come with an expiry date and require some very painful political decisions very soon â€” as they should. | G210: 1 | H210: 0 | I210: 0 | J210: 0 | K210: 1 | L210: 0 | M210: 1 | N210: 0 | O210: 0 | P210: 11 | Q210: 1425 | R210: 0.214 | S210: 0.243 | T210: 0.349 | U210: 0.31 | V210: 0.5 | W210: 0.304 | X210: 0.372 | Y210: 0.713 | Z210: 0.4 | AA210: 0.5 | AB210: 0.277 | AC210: 0.2285 | AD210: Title: The Two Things Worrying U.S. Military Officials About Israel and Hamas. Title: The Two Things Worrying U.S. Military Officials About Israel and Hamas. First Paragraph: Step back far enough, and you can see exactly what is driving so much geopolitics today: Ukraine is trying to join the West. Israel is trying to join a new Middle East. And Russia and Iran have teamed up to try to block both. Unfortunately, the new G.O.P. House speaker, Mike Johnson, is either too inexperienced or too ideological (or both) to see this (or to care). He is pushing a budget that would help Israel better defend itself but would deprive Ukraine of essential U.S. economic and military assistance to beat back Russiaâ€™s onslaught. And heâ€™s conditioned even the $14.3 billion the administration wants to send to Israel on President Biden agreeing to strip the same amount from funds added for the Internal Revenue Service so it could better collect taxes from cheaters. (Attention, Israel lobby: Do not go along with that game. Next time, aid for Israel will be tied to extreme G.O.P. positions on abortion or guns.) Thank goodness Johnson was not the speaker during World War II; he and his myopic members might have pressed to fund the war against the Germans in Europe but not against the Japanese in the Pacific. Or they would have agreed to Lend-Lease assistance for the allies only if President Franklin Roosevelt would eliminate the I.R.S. altogether. More guns, more butter, no taxes and two fronts. If it sounds like an utterly incoherent worldview that would undermine the American global leadership that has shaped a world weâ€™ve thrived in for the past century, itâ€™s because it is. And if it feels as if House G.O.P. leaders are small thinkers in a big time, itâ€™s because they are. They are shameless, shameful and dangerous. Please do our country a favor and audition for Fox News on some other issue. Because this IS a big moment â€” comparable to 1945 or 1989. If Ukraine is able to escape Russiaâ€™s grasp and eventually join NATO and the European Union â€” with its formidable army, agricultural exports and technology prowess â€” it would be a giant boost for a Europe whole and free. And if Israel can be maneuvered back to the bargaining table for a two-state solution with the Palestinian Authority â€” to pave the way for normalization between the Jewish state and Saudi Arabia â€” it would be a huge boost for a new, more pluralistic Middle East built around Palestinians, other Arabs and Israelis focused on strengthening their peopleâ€™s resilience for the future and not their resistance to each other and to the West. If these tectonic shifts can happen, the post-post-Cold War world has a far greater chance to handle other global challenges, like climate change, than if these shifts are stymied. But you donâ€™t need to speak Arabic, Hebrew, Persian, Russian or Ukrainian to understand that Iran-backed Hamas launched its war to stymie the Saudi-Israel normalization and prevent Tehran from being isolated, and that Vladimir Putin launched his war to stop Ukraine from expanding a Europe whole and free and prevent Moscow from being isolated. Russia under Putin and Iran under its supreme leader, Ayatollah Ali Khamenei, have a lot in common, argued the Russia expert Leon Aron, the author of â€œRiding the Tiger: Vladimir Putinâ€™s Russia and the Uses of War.â€ â€œBoth leaders have nothing to offer their people other than quasi-religious wars which enable them to stay in power by keeping their countries either at war or primed for war,â€ he told me. And both leaders are gunning for other countries whose aspirations are the antithesis of Russiaâ€™s and Iranâ€™s poisonous core regime identities. â€œUkraine proves that there can be a Slavic, Orthodox country, very close to Russia ethnically â€” yet free, democratic and thriving, with a Western political and economic orientation and not needing a state of war with the West or to be a police state like Belarus or a military dictatorship like Russia,â€ Aron said. Meanwhile, normalization of relations between the Jewish state and Saudi Arabia, the birthplace of Islam, would very likely pave the way for normalization between Israel and the most populous Muslim country in the world, Indonesia, as well as Malaysia and maybe later even Pakistan. It would prove that Jews and Muslims arenâ€™t destined to be forever in conflict and can revive the not always harmonious â€” but often harmonious â€” relations their communities enjoyed throughout much of history before the Palestinian conflict. As I said, nothing would have isolated Iran more. And Hamas knew that if Israel was able to normalize with Saudi Arabia on terms that would satisfy the more moderate Palestinian Authority in the West Bank and bring it significant financial advantages and more legitimacy, the Hamas Gaza resistance-forever model would have been totally isolated. So Hamas launched this war knowing it would bring death and ruin not only to many Israelis but also to many more of its own innocent civilians. Disgusting. Iran knew the same. All of this has created a huge opportunity for Putin. He welcomed a Hamas delegation to Moscow last week, and he has an expanding relationship with Iran underway; Iran is supplying Putin with drones and missiles to kill Ukrainians, in return for cybertechnologies, advanced aircraft and possibly antiaircraft equipment for Tehran. Itâ€™s a win-win-win for Putin. By helping Iran fuel the flames of a war between Israel and Iranâ€™s Middle East proxies, Putin knows he is forcing the U.S. to send more spare parts, Patriot missiles and 155-millimeter artillery shells to Israel instead of to Ukraine. And if that flow of arms to Kyiv is then cut off by Johnson and the House G.O.P., all Putin needs to do is count the days until Donald Trump is re-elected and Ukraine is his â€” or so he probably assumes. Plus all the instability drives up oil prices! While Republicans play dangerous games with military and economic aid, here are the two things that U.S. military officials tell me they are worried about: They believe that the Israelis want to take just Gaza City, where the core of Hamas military and manpower infrastructure is, and then use that as a launching pad for more tactical attacks on Hamasâ€™s leadership and rocket launchers in the rest of Gaza â€” without occupying it all. But Israelâ€™s military advance is already encountering a common challenge in urban warfare: You get stalled in the alleyways and then call in air power to blow away the enemy and anyone else nearby, leading to significant civilian casualties. The U.S. cannot ignore or defend that strategy for much longer, U.S. officials say. Second, the U.S. still sees a giant hole in the heart of Israelâ€™s strategy: Who will govern Gaza if and when Hamas is evicted? The only likely possibility is the Palestinian Authority in Ramallah, in the West Bank. But the only way those Palestinian leaders will assume that role is if Israel permits their capabilities to grow â€” provided they get their act together â€” and if Israel is seen as advancing a two-state solution. But the current government of Benjamin Netanyahu is dedicated to annexing the West Bank. So it looks as if Israelâ€™s army is reoccupying Gaza to eventually turn it over to some kind of legitimate Palestinian Authority â€” while Israelâ€™s extreme right-wing politicians and settlers are working overtime to delegitimize that authority and drive Palestinians out of the West Bank. This is a strategic contradiction. Israel actually needs a wartime peace process with the Palestinian Authority. The cold hard truth is this: Israel cannot get out of Gaza and sustain Western support without a credible Palestinian partner to govern there, and Ukraine cannot sustain Western support unless it makes substantial gains against Putinâ€™s army this winter or decides thatâ€™s impossible and agrees to some kind of dirty deal. That is, some kind of territorial compromise with Putin in return for a NATO security guarantee and a pathway to the European Union. No Western leaders are ready to say that out loud to Kyiv, but they all know it and believe it: Western support for Ukraine cannot and will not be there for an endless war of attrition. Thatâ€™s why today America must help Israel and Ukraine to blunt the Russia-Iran axis in their theaters. But the morning after their wars, Israel and Ukraine are going to have to face some very hard choices. Because while we may write big checks to both, they will not be blank checks. Each will come with an expiry date and require some very painful political decisions very soon â€” as they should. | AE210: 45232 | AF210: 45232 | AG210: 2023 | AH210: israel | AI210: iran | AJ210: netanyahu
A211: 210 | B211: 45231 | C211: Aaron Boxerman | D211: The New York Times | E211: Israel Confirms Deaths of 15 Soldiers in Ground Invasion of Gaza | F211: The soldiersâ€™ deaths were the first publicly confirmed by the Israeli military inside Gaza since an invasion began on Friday. At least 15 Israeli soldiers have been killed in battles in northern Gaza since Tuesday as its forces press deeper into the enclave, attacking dozens of targets affiliated with its Hamas rulers, the Israeli military said. The 15 deaths, mostly of infantry soldiers, were the first casualties inside Gaza publicly confirmed by Israelâ€™s military since it launched a ground invasion on Friday, as fighting appeared to intensify and its forces pushed closer to Gaza City, the biggest city in the territory. The military wing of Hamas said on Telegram on Tuesday that its fighters had ambushed some Israeli soldiers at a building in Beit Hanoun in northern Gaza. Neither sideâ€™s account of the fighting could be independently confirmed. In Israel, a small country in which military conscription is a mandatory rite of passage for many Jewish citizens, the soldiersâ€™ names and faces were plastered on the home pages of most news websites. Others were read out live on Israeli television when the military announced their deaths on Wednesday. The Israeli military said it has struck more than 11,000 targets in the Gaza Strip since Oct. 7, when it launched an intense campaign of airstrikes in response to a Hamas attack that killed some 1,400 people in Israel and saw just over 200 people taken hostage. The scale of the bombardment exceeds that of any of its previous wars with Palestinian militants in the 140-square-mile enclave. The toll of the ground invasion is only starting to become clear. On Tuesday, Israeli forces took over what they said was a Hamas military stronghold in western Jabaliya, a densely packed residential area north of Gaza City, claiming to kill more than 50 militants. There was no immediate comment by Hamas. | G211: 0 | H211: 0 | I211: 0 | J211: 0 | K211: 1 | L211: 0 | M211: 0 | N211: 0 | O211: 0 | P211: 11 | Q211: 307 | R211: 0.102 | S211: 0.108 | T211: 0.076 | U211: 0.5 | V211: 0.5 | W211: 0.071 | X211: 0.198 | Y211: 0.176 | Z211: 0.117 | AA211: 0.5 | AB211: 0.5 | AC211: 0.105 | AD211: Title: Israel Confirms Deaths of 15 Soldiers in Ground Invasion of Gaza. Title: Israel Confirms Deaths of 15 Soldiers in Ground Invasion of Gaza. First Paragraph: The soldiersâ€™ deaths were the first publicly confirmed by the Israeli military inside Gaza since an invasion began on Friday. At least 15 Israeli soldiers have been killed in battles in northern Gaza since Tuesday as its forces press deeper into the enclave, attacking dozens of targets affiliated with its Hamas rulers, the Israeli military said. The 15 deaths, mostly of infantry soldiers, were the first casualties inside Gaza publicly confirmed by Israelâ€™s military since it launched a ground invasion on Friday, as fighting appeared to intensify and its forces pushed closer to Gaza City, the biggest city in the territory. The military wing of Hamas said on Telegram on Tuesday that its fighters had ambushed some Israeli soldiers at a building in Beit Hanoun in northern Gaza. Neither sideâ€™s account of the fighting could be independently confirmed. In Israel, a small country in which military conscription is a mandatory rite of passage for many Jewish citizens, the soldiersâ€™ names and faces were plastered on the home pages of most news websites. Others were read out live on Israeli television when the military announced their deaths on Wednesday. The Israeli military said it has struck more than 11,000 targets in the Gaza Strip since Oct. 7, when it launched an intense campaign of airstrikes in response to a Hamas attack that killed some 1,400 people in Israel and saw just over 200 people taken hostage. The scale of the bombardment exceeds that of any of its previous wars with Palestinian militants in the 140-square-mile enclave. The toll of the ground invasion is only starting to become clear. On Tuesday, Israeli forces took over what they said was a Hamas military stronghold in western Jabaliya, a densely packed residential area north of Gaza City, claiming to kill more than 50 militants. There was no immediate comment by Hamas. | AE211: 45231 | AF211: 45231 | AG211: 2023 | AH211: israeli | AI211: israel | AJ211: gaza
A212: 211 | B212: 45231 | C212: Farnaz Fassihi | D212: The New York Times | E212: After Years of Vowing to Destroy Israel, Iran Faces a Dilemma | F212: With Israel bent on crushing Iranâ€™s ally Hamas, Tehran must decide whether it and the proxy militias it arms and trains will live up to its fiery rhetoric. For more than four decades, Iranâ€™s rulers have pledged to destroy Israel. The supreme leader, Ayatollah Ali Khamenei, rarely appears in public without wearing a black-and-white checkered Palestinian kaffiyeh. Iranian military commanders gloat over training and arming groups across the region that are enemies of Israel, including Hezbollah and Hamas. And when Hamas conducted the Oct. 7 terror attack on Israel that killed 1,400 people, Iranian officials praised it as a momentous achievement, shattering the Jewish stateâ€™s sense of security. Now Iran faces a dilemma, weighing how it and its proxy militias â€” known as the axis of resistance â€” should respond to Israelâ€™s invasion of Gaza and whether to bolster its revolutionary credentials at the risk of igniting a broader regional war. More than 8,000 Palestinians have been killed, according to the Gaza Health Ministry. â€œThere is no need for Iran to directly get involved in the war and attack Israel itself because it has the resistance axis militia who follow Iranâ€™s policies and strategies and act on its behalf,â€ said Nasser Imani, an analyst close to the government, in a telephone interview from Tehran. â€œRight now Iran is in control mode â€” it is telling all of them, including Hezbollah, to keep things boiling but have restraint.â€ For the time being, Iranian officials are publicly signaling they do not want a full-scale war. â€œI want to reiterate that we are not pursuing the spreading of this war,â€ Iranâ€™s foreign minister, Hossein Amir Abdollahian, said in a recent interview at Iranâ€™s mission to the United Nations. He was in New York to attend U.N. meetings related to the war. But, he added, â€œThe region is at a boiling point and any moment it may explode and this may be unavoidable. If this happens, all sides will lose control.â€ He warned that regional militias in Lebanon, Yemen, Iraq and Syria could open multiple fronts against Israel, with a high potential â€œthat the result will be that things will not go the way that Israelâ€™s regime wants.â€ He did not elaborate on what would prompt the groups, which he said act independently. Still, Iran does not want regional war, which carries risks for the nation and its religious rulers, according to three Iranians connected to the government who are familiar with internal deliberations and insisted on anonymity to discuss sensitive security matters. The military capabilities of its allies could be significantly diminished by a protracted battle with Israel, and even more so if the U.S. military enters the fray. The Islamic Republic views the militias as its extended arms of influence, able to strike while affordng Tehran a measure of deniability. They give Iran leverage in international negotiations and a means of tilting the balance of power in the Middle East away from archenemies like Israel and the United States, and rivals like Saudi Arabia. But if Iran does nothing, its fiery leaders risk losing credibility among constituents and allies. Some Iranian hard-line conservatives have questioned why Iranâ€™s actions are not matching its rhetoric to â€œfree Al Quds,â€ or Jerusalem, from Israelâ€™s rule. Many supporters of Iranâ€™s government have even symbolically signed up as volunteers to be deployed to Gaza and fight Israel. | G212: 0 | H212: 0 | I212: 0 | J212: 0 | K212: 1 | L212: 0 | M212: 0 | N212: 0 | O212: 0 | P212: 11 | Q212: 560 | R212: 0.08 | S212: 0.105 | T212: 0.306 | U212: 0.5 | V212: 0.5 | W212: 0.112 | X212: 0.129 | Y212: 0.406 | Z212: 0.156 | AA212: 0.5 | AB212: 0.5 | AC212: 0.0925 | AD212: Title: After Years of Vowing to Destroy Israel, Iran Faces a Dilemma. Title: After Years of Vowing to Destroy Israel, Iran Faces a Dilemma. First Paragraph: With Israel bent on crushing Iranâ€™s ally Hamas, Tehran must decide whether it and the proxy militias it arms and trains will live up to its fiery rhetoric. For more than four decades, Iranâ€™s rulers have pledged to destroy Israel. The supreme leader, Ayatollah Ali Khamenei, rarely appears in public without wearing a black-and-white checkered Palestinian kaffiyeh. Iranian military commanders gloat over training and arming groups across the region that are enemies of Israel, including Hezbollah and Hamas. And when Hamas conducted the Oct. 7 terror attack on Israel that killed 1,400 people, Iranian officials praised it as a momentous achievement, shattering the Jewish stateâ€™s sense of security. Now Iran faces a dilemma, weighing how it and its proxy militias â€” known as the axis of resistance â€” should respond to Israelâ€™s invasion of Gaza and whether to bolster its revolutionary credentials at the risk of igniting a broader regional war. More than 8,000 Palestinians have been killed, according to the Gaza Health Ministry. â€œThere is no need for Iran to directly get involved in the war and attack Israel itself because it has the resistance axis militia who follow Iranâ€™s policies and strategies and act on its behalf,â€ said Nasser Imani, an analyst close to the government, in a telephone interview from Tehran. â€œRight now Iran is in control mode â€” it is telling all of them, including Hezbollah, to keep things boiling but have restraint.â€ For the time being, Iranian officials are publicly signaling they do not want a full-scale war. â€œI want to reiterate that we are not pursuing the spreading of this war,â€ Iranâ€™s foreign minister, Hossein Amir Abdollahian, said in a recent interview at Iranâ€™s mission to the United Nations. He was in New York to attend U.N. meetings related to the war. But, he added, â€œThe region is at a boiling point and any moment it may explode and this may be unavoidable. If this happens, all sides will lose control.â€ He warned that regional militias in Lebanon, Yemen, Iraq and Syria could open multiple fronts against Israel, with a high potential â€œthat the result will be that things will not go the way that Israelâ€™s regime wants.â€ He did not elaborate on what would prompt the groups, which he said act independently. Still, Iran does not want regional war, which carries risks for the nation and its religious rulers, according to three Iranians connected to the government who are familiar with internal deliberations and insisted on anonymity to discuss sensitive security matters. The military capabilities of its allies could be significantly diminished by a protracted battle with Israel, and even more so if the U.S. military enters the fray. The Islamic Republic views the militias as its extended arms of influence, able to strike while affordng Tehran a measure of deniability. They give Iran leverage in international negotiations and a means of tilting the balance of power in the Middle East away from archenemies like Israel and the United States, and rivals like Saudi Arabia. But if Iran does nothing, its fiery leaders risk losing credibility among constituents and allies. Some Iranian hard-line conservatives have questioned why Iranâ€™s actions are not matching its rhetoric to â€œfree Al Quds,â€ or Jerusalem, from Israelâ€™s rule. Many supporters of Iranâ€™s government have even symbolically signed up as volunteers to be deployed to Gaza and fight Israel. | AE212: 45231 | AF212: 45231 | AG212: 2023 | AH212: iran | AI212: israel | AJ212: council
A213: 212 | B213: 45228 | C213: Vivian Yee | D213: The New York Times | E213: Israel says Al Shifa hospital conceals underground Hamas command centers, which the group denies. | F213: To people in Gaza, Al Shifa is the biggest and most advanced hospital around â€” a lifeline, in normal times, and now a place of refuge from relentless Israeli airstrikes. More than 60,000 people are sheltering there. But to the Israeli military, it is a threat, and, perhaps, a target. On Friday, hours before the Israeli military stepped up its bombardment of Gaza in retaliation for Hamasâ€™s mass killings of Israelis three weeks ago, it held a news conference in which it said that Al Shifa conceals underground command centers for Hamas â€” raising fears that the military was laying the groundwork for attacking the hospital. Hamas â€œdoes its command and control in different departments of the hospital,â€ said Rear Adm. Daniel Hagari, the chief spokesman for the Israeli military, speaking in English and citing intelligence sources that he did not release. He displayed an illustrated map of the hospital marking what he said were several underground Hamas installations in the complex. â€œThis is where they direct rocket attacks, command Hamas forces,â€ he said at the news conference held in Tel Aviv. He also played a recording of a call, whose origins he did not specify, in which an unidentified man tells a woman that Hamasâ€™s military headquarters are below the hospital. â€œGod forbid!â€ the woman, who is also unnamed, replies in the audio recording. Salama Marouf, the head of the Hamas-run Gaza government media office, denied the accusation in a news conference on Friday night, saying Israel had â€œfailed to provide a single piece of evidenceâ€ supporting its claims about Al Shifa. He said the recording Adm. Hagari cited was â€œfabricated.â€ On Saturday, Adm. Hagari said the news conference about the hospital was part of a continuing effort to â€œexposeâ€ Hamasâ€™s â€œexploitation of the civilian population in the Gaza Strip.â€ Also on Saturday, Israel released a pair of videos that it said showed Palestinian prisoners who had been â€œinvolvedâ€ in Hamasâ€™s Oct. 7 raids on Israel speaking about Hamasâ€™s use of Al Shifa. â€œI know, for example, according to what Iâ€™ve heard, the Shifa Hospital, theyâ€™re using it, theyâ€™re hiding there,â€ says one, who describes himself in the video as a paramedic. Israel has long viewed civilian infrastructure such as homes, malls and places of worship as legitimate targets for its strikes, saying Hamas runs operations in those kinds of places, using civilians as human shields. Israel says that when attacking, it attempts to distinguish between civilians and combatants. Gazaâ€™s health ministry has released the names of at least 1,500 children under the age of 10 who it says were killed in Israeli airstrikes from Oct. 7 to Oct. 26. | G213: 0 | H213: 0 | I213: 0 | J213: 0 | K213: 1 | L213: 0 | M213: 0 | N213: 0 | O213: 0 | P213: 14 | Q213: 441 | R213: 0.206 | S213: 0.593 | T213: 0.329 | U213: 0.5 | V213: 0.5 | W213: 0.26 | X213: 0.229 | Y213: 0.354 | Z213: 0.526 | AA213: 0.5 | AB213: 0.5 | AC213: 0.3995 | AD213: Title: Israel says Al Shifa hospital conceals underground Hamas command centers, which the group denies.. Title: Israel says Al Shifa hospital conceals underground Hamas command centers, which the group denies.. First Paragraph: To people in Gaza, Al Shifa is the biggest and most advanced hospital around â€” a lifeline, in normal times, and now a place of refuge from relentless Israeli airstrikes. More than 60,000 people are sheltering there. But to the Israeli military, it is a threat, and, perhaps, a target. On Friday, hours before the Israeli military stepped up its bombardment of Gaza in retaliation for Hamasâ€™s mass killings of Israelis three weeks ago, it held a news conference in which it said that Al Shifa conceals underground command centers for Hamas â€” raising fears that the military was laying the groundwork for attacking the hospital. Hamas â€œdoes its command and control in different departments of the hospital,â€ said Rear Adm. Daniel Hagari, the chief spokesman for the Israeli military, speaking in English and citing intelligence sources that he did not release. He displayed an illustrated map of the hospital marking what he said were several underground Hamas installations in the complex. â€œThis is where they direct rocket attacks, command Hamas forces,â€ he said at the news conference held in Tel Aviv. He also played a recording of a call, whose origins he did not specify, in which an unidentified man tells a woman that Hamasâ€™s military headquarters are below the hospital. â€œGod forbid!â€ the woman, who is also unnamed, replies in the audio recording. Salama Marouf, the head of the Hamas-run Gaza government media office, denied the accusation in a news conference on Friday night, saying Israel had â€œfailed to provide a single piece of evidenceâ€ supporting its claims about Al Shifa. He said the recording Adm. Hagari cited was â€œfabricated.â€ On Saturday, Adm. Hagari said the news conference about the hospital was part of a continuing effort to â€œexposeâ€ Hamasâ€™s â€œexploitation of the civilian population in the Gaza Strip.â€ Also on Saturday, Israel released a pair of videos that it said showed Palestinian prisoners who had been â€œinvolvedâ€ in Hamasâ€™s Oct. 7 raids on Israel speaking about Hamasâ€™s use of Al Shifa. â€œI know, for example, according to what Iâ€™ve heard, the Shifa Hospital, theyâ€™re using it, theyâ€™re hiding there,â€ says one, who describes himself in the video as a paramedic. Israel has long viewed civilian infrastructure such as homes, malls and places of worship as legitimate targets for its strikes, saying Hamas runs operations in those kinds of places, using civilians as human shields. Israel says that when attacking, it attempts to distinguish between civilians and combatants. Gazaâ€™s health ministry has released the names of at least 1,500 children under the age of 10 who it says were killed in Israeli airstrikes from Oct. 7 to Oct. 26. | AE213: 45228 | AF213: 45228 | AG213: 2023 | AH213: trucks | AI213: aid | AJ213: hospital
A214: 213 | B214: 45228 | C214: Thomas Friedman | D214: The New York Times | E214: The Israeli Officials I Speak With Tell Me They Know Two Things for Sure | F214: I am watching the Israel-Hamas war and thinking about one of the world leaders Iâ€™ve most admired: Manmohan Singh. He was Indiaâ€™s prime minister in late November 2008 when 10 Pakistani jihadist militants from the Lashkar-e-Taiba group, widely believed to be linked to Pakistanâ€™s military intelligence, infiltrated India and killed more than 160 people in Mumbai, including 61 at two luxury hotels. What was Singhâ€™s military response to Indiaâ€™s Sept. 11? He did nothing. Singh never retaliated militarily against the nation of Pakistan or Lashkar camps in Pakistan. It was a remarkable act of restraint. What was the logic? In his book â€œChoices: Inside the Making of Indiaâ€™s Foreign Policy,â€ Indiaâ€™s foreign secretary at the time, Shivshankar Menon, explained, making these key points: â€œI myself pressed at that time for immediate visible retaliationâ€ against the jihadist bases or against Pakistani military intelligence, â€œwhich was clearly complicit,â€ Menon wrote. â€œTo have done so would have been emotionally satisfying and gone some way toward erasing the shame of the incompetence that Indiaâ€™s police and security agencies displayed.â€He continued, â€œBut on sober reflection and in hindsight, I now believe that the decision not to retaliate militarily and to concentrate on diplomatic, covert and other means was the right one for that time and place.â€ Chief among the reasons, Menon said, was that any military response would have quickly obscured just how outrageous and terrible the raid on Indian civilians and tourists was; â€œthe fact of a terrorist attack from Pakistan on India with official involvement on the Pakistan sideâ€ would have been lost. Once India retaliated, the world would immediately have had what Menon called a â€œho-hum reaction.â€ Just another Pakistani-Indian dust-up â€” nothing unusual here. Moreover, Menon wrote, â€œan Indian attack on Pakistan would have united Pakistan behind the Pakistan Army, which was in increasing domestic disrepute,â€ and â€œan attack on Pakistan would also have weakened the civilian government in Pakistan, which had just been elected to power and which sought a much better relationship with India than the Pakistan Army was willing to consider.â€ He continued, â€œA war scare, and maybe even a war itself, was exactly what the Pakistan Army wanted to buttress its internal position.â€ In addition, he wrote, â€œa war, even a successful war, would have imposed costs and set back the progress of the Indian economy just when the world economy in November 2008 was in an unprecedented financial crisis.â€ In conclusion, said Menon, â€œby not attacking Pakistan, India was free to pursue all legal and covert means to achieve its goals of bringing the perpetrators to justice, uniting the international community to force consequences on Pakistan for its behavior and to strengthen the likelihood that such an attack would not take place again.â€ I understand that Israel is not India â€” a country of 1.4 billion people, covering a massive territory. The loss of more than 160 people in Mumbai, some of them tourists, was not felt in every home and hamlet, as were Hamasâ€™s killing of roughly 1,400 Israelis, the maiming of countless others and the kidnapping of more than 200 people. Pakistan also has nuclear weapons to deter retaliation. Nevertheless, it is instructive to reflect on the contrast between Indiaâ€™s response to the Mumbai terrorist attack and Israelâ€™s response to the Hamas slaughter. After the initial horror at the sheer barbarism of the Hamas onslaught on Israeli children, older adults and a dance party, what happened? The narrative quickly shifted to the brutality of the Israeli counterattack on Gazan civilians, among whom Hamas has embedded itself. The massive Israeli counterstrike overshadowed Hamasâ€™s terrorism and instead made the organization a hero to some. It has also forced Israelâ€™s new Arab allies in the Abraham Accords to distance themselves from the Jewish state. Meanwhile, with some 360,000 reservists called up, Israelâ€™s economy will almost certainly be depressed if Israelâ€™s ouster of Hamas from Gaza takes months, as predicted. The economy is already expected to shrink more than 10 percent on an annualized basis for the last three months of the year. This after being ranked by The Economist as the fourth-best-performing economy among O.E.C.D. countries in 2022. On a personal level, I am appalled by the reaction of those studnts and progressives who sided with Hamas against Israel â€” in some cases, even before Israel retaliated â€” as if the Jewish people were not entitled to either self-determination or self-defense in any part of their ancestral homeland. This backlash also fails to take into account that Israel, for all its faults, is a multicultural society where almost half of graduating doctors today are Arabs or Druze. Or that Hamas is a militant, Islamist organization that does not tolerate dissent or L.G.B.T.Q. individuals and has been dedicated to wiping the Jewish state off the face of the earth. So I have sympathy for the terrible choices that Israelâ€™s government faced after the worst slaughter of Jews since the Holocaust. But it was precisely because I closely followed Singhâ€™s unique reaction to the Mumbai terrorist attack that I immediately advocated a much more targeted, fully thought-through response by Israel. It should have called this Operation Save Our Hostages and focused on capturing and killing the kidnappers of children and grandparents. Every parent could understand that. Instead, Benjamin Netanyahuâ€™s government immediately raced into a plan to, as Defense Minister Yoav Gallant put it, â€œwipe outâ€ Hamas â€œfrom the face of the earth.â€ And in three weeks Israel has inflicted easily more than triple the number of civilian casualties and caused far more destruction in Gaza than Israel suffered, while committing itself to taking military control of Gaza â€” an operation, on a relative population basis, that is roughly equivalent to the United States deciding almost overnight to occupy half of Mexico. The Israeli plan, according to Netanyahu, will be a â€œlong and difficultâ€ battle to â€œdestroy the military and governmental capabilities of Hamas and bring the hostages home.â€ As I said, Israel is not India, and there is no way that it could be expected to turn the other cheek â€” not in that neighborhood. But what is Netanyahuâ€™s plan? The Israeli officials I speak with tell me they know two things for sure: Hamas will never again govern Gaza, and Israel will not govern a post-Hamas Gaza. They suggest that they will set up an arrangement similarly seen in parts of the West Bank today, with Palestinians in Gaza administering day-to-day life and Israeli military and Shin Bet security teams providing the muscle behind the scenes. This is a half-baked plan. Who are these Palestinians who will be enlisted to govern Gaza on Israelâ€™s behalf? What happens the morning after a Palestinian working for Israel in Gaza is found murdered in an alley with a note pinned to his chest: â€œTraitor,â€™â€™ signed â€œthe Hamas underground.â€ Moreover, who is going to pay for Israelâ€™s control of, health care for and education of Gazaâ€™s 2.2 million people? Please raise your hand if you think the European Union, the Gulf Arab states or the substantial progressive caucus in the Democratic Party in the U.S. House of Representatives will fund an indefinite Israeli oversight of Gaza â€” while Netanyahu and his band of Jewish supremacists are pledged to annex the West Bank without equal rights for the Palestinians there. The cost of occupying Gaza could overstretch the Israeli military and economy for years to come. On top of it all, how is Israel going to manage such a complex operation when there is â€” for good reason â€” scant trust in Netanyahu? Just on Saturday he pointed to the heads of Israeli military intelligence and Shin Bet as responsible for missing the Hamas surprise attack while excusing himself of any blame. A day later, an outraged Israeli public forced the prime minister to retract his wartime recriminations against his colleagues. But the damage was done. Netanyahu does not have a team of rivals supporting him. He has a team of people being asked to make excruciating long-term choices while knowing their prime minister is a person of such low character that he will blame them for everything that goes wrong and hog all credit for anything that goes right. In sum, dear reader, I understand why Israel believes it needs to destroy Hamas and thereby deter others in the neighborhood from ever contemplating such a thing. But the view from Washington is that Israelâ€™s leadership does not have a viable plan to win or a leader who can navigate the stresses and complexity of this crisis. Israel needs to know that the tolerance of its American ally for massive civilian casualties in Gaza in an open-ended military operation is not unlimited. In fact, we may soon be approaching the limit. Israel should keep the door open for a humanitarian cease-fire and prisoner exchange that will also allow Israel to pause and reflect on exactly where it is going with its rushed Gaza military operation â€” and the price it could pay over the long haul. That is why I raise the Indian example. Because targeted use of force with limited, achievable goals may serve Israelâ€™s long-term security and prosperity more than an open-ended war to eradicate Hamas. I hope Israel is stress-testing the costs and benefits of both approaches. A pause could also allow the people of Gaza to take stock of what Hamasâ€™s attack on Israel â€” and Israelâ€™s totally predictable response â€” has done to their lives, families, homes and businesses. What exactly did Hamas think it would accomplish with this war for the people of Gaza, thousands of whom were traveling to work in Israel every day or exporting agricultural products and other goods across the Gaza-Israel border just a few weeks ago? Hamas has gotten way too much understanding and not enough hard questions. I want to see Hamasâ€™s leaders come out from their tunnels under hospitals and look their people, and the worldâ€™s media, in the eye and tell everyone why they thought it was such a great idea to mutilate and kidnap Israeli children and grandmothers and trigger this terrible blowback on the children and grandmothers of their Gaza neighbors â€” not to mention their own. I have always believed that you can reduce the Israeli-Palestinian conflict since the early 1900s to one line: conflict, timeout, conflict, timeout, conflict, timeout, conflict, timeout, conflict and timeout. The most important difference between the parties is what they each did during the timeouts. Israel built an impressive society and economy, even if flawed, and Hamas took nearly all of its resources and built attack tunnels. Please, Israel, donâ€™t get lost in those tunnels. | G214: 0 | H214: 0 | I214: 1 | J214: 0 | K214: 1 | L214: 1 | M214: 1 | N214: 0 | O214: 0 | P214: 14 | Q214: 1774 | R214: 0.553 | S214: 0.615 | T214: 0.5 | U214: 0.144 | V214: 0.5 | W214: 0.281 | X214: 0.493 | Y214: 0.105 | Z214: 0.102 | AA214: 0.5 | AB214: 0.5 | AC214: 0.584 | AD214: Title: The Israeli Officials I Speak With Tell Me They Know Two Things for Sure. Title: The Israeli Officials I Speak With Tell Me They Know Two Things for Sure. First Paragraph: I am watching the Israel-Hamas war and thinking about one of the world leaders Iâ€™ve most admired: Manmohan Singh. He was Indiaâ€™s prime minister in late November 2008 when 10 Pakistani jihadist militants from the Lashkar-e-Taiba group, widely believed to be linked to Pakistanâ€™s military intelligence, infiltrated India and killed more than 160 people in Mumbai, including 61 at two luxury hotels. What was Singhâ€™s military response to Indiaâ€™s Sept. 11? He did nothing. Singh never retaliated militarily against the nation of Pakistan or Lashkar camps in Pakistan. It was a remarkable act of restraint. What was the logic? In his book â€œChoices: Inside the Making of Indiaâ€™s Foreign Policy,â€ Indiaâ€™s foreign secretary at the time, Shivshankar Menon, explained, making these key points: â€œI myself pressed at that time for immediate visible retaliationâ€ against the jihadist bases or against Pakistani military intelligence, â€œwhich was clearly complicit,â€ Menon wrote. â€œTo have done so would have been emotionally satisfying and gone some way toward erasing the shame of the incompetence that Indiaâ€™s police and security agencies displayed.â€He continued, â€œBut on sober reflection and in hindsight, I now believe that the decision not to retaliate militarily and to concentrate on diplomatic, covert and other means was the right one for that time and place.â€ Chief among the reasons, Menon said, was that any military response would have quickly obscured just how outrageous and terrible the raid on Indian civilians and tourists was; â€œthe fact of a terrorist attack from Pakistan on India with official involvement on the Pakistan sideâ€ would have been lost. Once India retaliated, the world would immediately have had what Menon called a â€œho-hum reaction.â€ Just another Pakistani-Indian dust-up â€” nothing unusual here. Moreover, Menon wrote, â€œan Indian attack on Pakistan would have united Pakistan behind the Pakistan Army, which was in increasing domestic disrepute,â€ and â€œan attack on Pakistan would also have weakened the civilian government in Pakistan, which had just been elected to power and which sought a much better relationship with India than the Pakistan Army was willing to consider.â€ He continued, â€œA war scare, and maybe even a war itself, was exactly what the Pakistan Army wanted to buttress its internal position.â€ In addition, he wrote, â€œa war, even a successful war, would have imposed costs and set back the progress of the Indian economy just when the world economy in November 2008 was in an unprecedented financial crisis.â€ In conclusion, said Menon, â€œby not attacking Pakistan, India was free to pursue all legal and covert means to achieve its goals of bringing the perpetrators to justice, uniting the international community to force consequences on Pakistan for its behavior and to strengthen the likelihood that such an attack would not take place again.â€ I understand that Israel is not India â€” a country of 1.4 billion people, covering a massive territory. The loss of more than 160 people in Mumbai, some of them tourists, was not felt in every home and hamlet, as were Hamasâ€™s killing of roughly 1,400 Israelis, the maiming of countless others and the kidnapping of more than 200 people. Pakistan also has nuclear weapons to deter retaliation. Nevertheless, it is instructive to reflect on the contrast between Indiaâ€™s response to the Mumbai terrorist attack and Israelâ€™s response to the Hamas slaughter. After the initial horror at the sheer barbarism of the Hamas onslaught on Israeli children, older adults and a dance party, what happened? The narrative quickly shifted to the brutality of the Israeli counterattack on Gazan civilians, among whom Hamas has embedded itself. The massive Israeli counterstrike overshadowed Hamasâ€™s terrorism and instead made the organization a hero to some. It has also forced Israelâ€™s new Arab allies in the Abraham Accords to distance themselves from the Jewish state. Meanwhile, with some 360,000 reservists called up, Israelâ€™s economy will almost certainly be depressed if Israelâ€™s ouster of Hamas from Gaza takes months, as predicted. The economy is already expected to shrink more than 10 percent on an annualized basis for the last three months of the year. This after being ranked by The Economist as the fourth-best-performing economy among O.E.C.D. countries in 2022. On a personal level, I am appalled by the reaction of those studnts and progressives who sided with Hamas against Israel â€” in some cases, even before Israel retaliated â€” as if the Jewish people were not entitled to either self-determination or self-defense in any part of their ancestral homeland. This backlash also fails to take into account that Israel, for all its faults, is a multicultural society where almost half of graduating doctors today are Arabs or Druze. Or that Hamas is a militant, Islamist organization that does not tolerate dissent or L.G.B.T.Q. individuals and has been dedicated to wiping the Jewish state off the face of the earth. So I have sympathy for the terrible choices that Israelâ€™s government faced after the worst slaughter of Jews since the Holocaust. But it was precisely because I closely followed Singhâ€™s unique reaction to the Mumbai terrorist attack that I immediately advocated a much more targeted, fully thought-through response by Israel. It should have called this Operation Save Our Hostages and focused on capturing and killing the kidnappers of children and grandparents. Every parent could understand that. Instead, Benjamin Netanyahuâ€™s government immediately raced into a plan to, as Defense Minister Yoav Gallant put it, â€œwipe outâ€ Hamas â€œfrom the face of the earth.â€ And in three weeks Israel has inflicted easily more than triple the number of civilian casualties and caused far more destruction in Gaza than Israel suffered, while committing itself to taking military control of Gaza â€” an operation, on a relative population basis, that is roughly equivalent to the United States deciding almost overnight to occupy half of Mexico. The Israeli plan, according to Netanyahu, will be a â€œlong and difficultâ€ battle to â€œdestroy the military and governmental capabilities of Hamas and bring the hostages home.â€ As I said, Israel is not India, and there is no way that it could be expected to turn the other cheek â€” not in that neighborhood. But what is Netanyahuâ€™s plan? The Israeli officials I speak with tell me they know two things for sure: Hamas will never again govern Gaza, and Israel will not govern a post-Hamas Gaza. They suggest that they will set up an arrangement similarly seen in parts of the West Bank today, with Palestinians in Gaza administering day-to-day life and Israeli military and Shin Bet security teams providing the muscle behind the scenes. This is a half-baked plan. Who are these Palestinians who will be enlisted to govern Gaza on Israelâ€™s behalf? What happens the morning after a Palestinian working for Israel in Gaza is found murdered in an alley with a note pinned to his chest: â€œTraitor,â€™â€™ signed â€œthe Hamas underground.â€ Moreover, who is going to pay for Israelâ€™s control of, health care for and education of Gazaâ€™s 2.2 million people? Please raise your hand if you think the European Union, the Gulf Arab states or the substantial progressive caucus in the Democratic Party in the U.S. House of Representatives will fund an indefinite Israeli oversight of Gaza â€” while Netanyahu and his band of Jewish supremacists are pledged to annex the West Bank without equal rights for the Palestinians there. The cost of occupying Gaza could overstretch the Israeli military and economy for years to come. On top of it all, how is Israel going to manage such a complex operation when there is â€” for good reason â€” scant trust in Netanyahu? Just on Saturday he pointed to the heads of Israeli military intelligence and Shin Bet as responsible for missing the Hamas surprise attack while excusing himself of any blame. A day later, an outraged Israeli public forced the prime minister to retract his wartime recriminations against his colleagues. But the damage was done. Netanyahu does not have a team of rivals supporting him. He has a team of people being asked to make excruciating long-term choices while knowing their prime minister is a person of such low character that he will blame them for everything that goes wrong and hog all credit for anything that goes right. In sum, dear reader, I understand why Israel believes it needs to destroy Hamas and thereby deter others in the neighborhood from ever contemplating such a thing. But the view from Washington is that Israelâ€™s leadership does not have a viable plan to win or a leader who can navigate the stresses and complexity of this crisis. Israel needs to know that the tolerance of its American ally for massive civilian casualties in Gaza in an open-ended military operation is not unlimited. In fact, we may soon be approaching the limit. Israel should keep the door open for a humanitarian cease-fire and prisoner exchange that will also allow Israel to pause and reflect on exactly where it is going with its rushed Gaza military operation â€” and the price it could pay over the long haul. That is why I raise the Indian example. Because targeted use of force with limited, achievable goals may serve Israelâ€™s long-term security and prosperity more than an open-ended war to eradicate Hamas. I hope Israel is stress-testing the costs and benefits of both approaches. A pause could also allow the people of Gaza to take stock of what Hamasâ€™s attack on Israel â€” and Israelâ€™s totally predictable response â€” has done to their lives, families, homes and businesses. What exactly did Hamas think it would accomplish with this war for the people of Gaza, thousands of whom were traveling to work in Israel every day or exporting agricultural products and other goods across the Gaza-Israel border just a few weeks ago? Hamas has gotten way too much understanding and not enough hard questions. I want to see Hamasâ€™s leaders come out from their tunnels under hospitals and look their people, and the worldâ€™s media, in the eye and tell everyone why they thought it was such a great idea to mutilate and kidnap Israeli children and grandmothers and trigger this terrible blowback on the children and grandmothers of their Gaza neighbors â€” not to mention their own. I have always believed that you can reduce the Israeli-Palestinian conflict since the early 1900s to one line: conflict, timeout, conflict, timeout, conflict, timeout, conflict, timeout, conflict and timeout. The most important difference between the parties is what they each did during the timeouts. Israel built an impressive society and economy, even if flawed, and Hamas took nearly all of its resources and built attack tunnels. Please, Israel, donâ€™t get lost in those tunnels. | AE214: 45228 | AF214: 45228 | AG214: 2023 | AH214: israel | AI214: iran | AJ214: netanyahu
... A292: 291 | B292: 44869 | C292: Thomas Friedman | D292: The New York Times | E292: The Israel We Knew Is Gone | F292: Imagine you woke up after the 2024 U.S. presidential election and found that Donald Trump had been re-elected and chose Rudy Giuliani for attorney general, Michael Flynn for defense secretary, Steve Bannon for commerce secretary, evangelical leader James Dobson for education secretary, Proud Boys former leader Enrique Tarrio for homeland security head and Marjorie Taylor Greene for the White House spokeswoman. â€œImpossible,â€ you would say. Well, think again. As Iâ€™ve noted before, Israeli political trends are often a harbinger of wider trends in Western democracies â€” Off Broadway to our Broadway. I hoped that the national unity government that came to power in Israel in June 2021 might also be a harbinger of more bipartisanship here. Alas, that government has now collapsed and is being replaced by the most far-far-right coalition in Israelâ€™s history. Lord save us if this is a harbinger of whatâ€™s coming our way. The coalition that Likud leader Bibi Netanyahu is riding back into power is the Israeli equivalent of the nightmare U.S. cabinet I imagined above. Only it is real â€” a rowdy alliance of ultra-Orthodox leaders and ultranationalist politicians, including some outright racist, anti-Arab Jewish extremists once deemed completely outside the norms and boundaries of Israeli politics. As it is virtually impossible for Netanyahu to build a majority coalition without the support of these extremists, some of them are almost certain to be cabinet ministers in the next Israeli government. As that previously unthinkable reality takes hold, a fundamental question will roil synagogues in America and across the globe: â€œDo I support this Israel or not support it?â€ It will haunt pro-Israel students on college campuses. It will challenge Arab allies of Israel in the Abraham Accords, who just wanted to trade with Israel and never signed up for defending a government there that is anti-Israeli Arab. It will stress those U.S. diplomats who have reflexively defended Israel as a Jewish democracy that shares Americaâ€™s values, and it will send friends of Israel in Congress fleeing from any reporter asking if America should continue sending billions of dollars in aid to such a religious-extremist-inspired government. You have not seen this play before, because no Israeli leader has â€œgone thereâ€ before. Netanyahu has been propelled into power by bedfellows who: see Israeli Arab citizens as a fifth column who canâ€™t be trusted; have vowed to take political control over judicial appointments; believe that Jewish settlements must be expanded so there is not an inch left anywhere in the West Bank for a Palestinian state; want to enact judicial changes that could freeze Netanyahuâ€™s ongoing corruption trial; and express contempt for Israelâ€™s long and strong embrace of L.G.B.T.Q. rights. We are talking about people like Itamar Ben-Gvir, who was convicted by an Israeli court in 2007 of incitement to racism and supporting a Jewish terrorist organization. Netanyahu personally forged an alliance between Ben-Gvirâ€™s Jewish Power party and Bezalel Smotrich, the leader of the Religious Zionism party, which turned them (shockingly for many Israelis) into the third-largest party in the country â€” giving Netanyahu the allies Likud needed to win a parliamentary majority in this weekâ€™s election. Smotrich is known for, among other things, suggesting that Israeli Jewish mothers should be separated from Arab mothers in the maternity wards of Israeli hospitals. He has long advocated outright Israeli annexation of the West Bank and argued that there is â€œno such thing as Jewish terrorismâ€ when it comes to settlers retaliating on their own against Palestinian violence. Netanyahu has increasingly sought over the years to leverage the energy of this illiberal Israeli constituency to win office, not unlike how Trump uses white nationalism, but Netanyahu never actually brought this radical element â€” like Ben-Gvir, who claims to have moderated because he has told his supporters to chant, â€œDeath to terrorists,â€ instead of, â€œDeath to Arabsâ€ â€” into his ruling faction or cabinet. As more of Netanyahuâ€™s allies in Likud split with him over his alleged criminal behavior and lying, however, Bibi had to reach further and further out of the mainstream of Israeli politics to get enough votes to rule and pass a law to abort his own trial and possible jail time. Netanyahu had fertile political soil to work with, the Yediot Ahronot Israeli newspaper columnist Nahum Barnea explained to me. There has been a dramatic upsurge in violence â€” stabbings, shootings, gang warfare and organized crime â€” by Israeli Arabs against other Israeli Arabs, and Israeli Arab gangs and organized crime against Israeli Jews, particularly in mixed communities. The result is that, â€œlike in America, â€˜policingâ€™ has become a huge issue in Israel in recent years,â€ said Barnea â€” and even though this upsurge started when Netanyahu was previously prime minister, he and his anti-Arab allies blamed it all on the Arabs and the national unity Israeli government. One election billboard summed up Netanyahuâ€™s campaign. It was, as Haaretz reporter Amos Harel reported, a â€œgloomy-looking one with the caption: â€˜Thatâ€™s it. Weâ€™ve had enough.â€™ It depicts outgoing Prime Minister Yair Lapid and his coalition partner, Mansour Abbas of the United Arab List.â€ Abbas is the rather amazing Israeli Arab religious party leader who recognizes the State of Israel and the searing importance of the Holocaust, and who was part of the now-fallen unity government. As Harel put it: â€œThe â€˜had enoughâ€™ message seems to have sunk in among supporters of Likud, Religious Zionism and the ultra-Orthodox parties. Itâ€™s likely that the message also helped Netanyahu win Tuesdayâ€™s election.â€ Among the critical factors, Harel wrote, was â€œhatred of Arabs and the desire to keep them out of positions of power.â€ But Netanyahu was also aided by the fact that while the right and the far right were highly energized by both growing fears of and distrust of Arabs â€” whether Israeli Arab citizens or Palestinians in the West Bank â€” their centrist and center-left opponents had no coherent or inspiring countermessage. As Barnea put it to me: â€œIsrael is not divided down the middle,â€ with 50 percent being pro-Netanyahu and the other 50 percent with a unified message and strategy opposing him. â€œNo, Israel is divided between the 50 percent who are pro-Netanyahu and the 50 percent who are pro-blocking Netanyahu. But that is all they can agree on,â€ Barnea said. And it showed in this election. And it wasnâ€™t enough. Why is all of this so dangerous? Moshe Halbertal, the Hebrew University Jewish philosopher, captured it well: For decades members of the Israeli right, a vast majority of whom were â€œsecurity hawks,â€ have believed that the Palestinians have never and will never accept a Jewish state next to them and therefore Israel needed to take whatever military means were necessary to protect itself from them. But Israeli hawkishness toward the Palestinians, explained Halbertal, â€œis now morphing into something new â€” a kind of general ultranationalismâ€ that not only rejects any notion of a Palestinian state but also views every Israeli Arab â€” who make up about 21 percent of Israelâ€™s population, nearly 20 percent of its doctors, about 25 percent of its nurses and almost half its pharmacists â€” as a potential terrorist. â€œWhat we are seeing is a shift in the hawkish right from a political identity built on focusing on the â€˜enemy outsideâ€™ â€” the Palestinians â€” to the â€˜enemy insideâ€™ â€” Israeli Arabs,â€ Halbertal said. Netanyahuâ€™s coalition has also attacked the vital independent institutions that underpin Israelâ€™s democracy and are responsible for, among other things, protecting minority rights. That is, the lower court system, the media and, most of all, the Supreme Court, which Netanyahu and his allies want brought under the political control of the right, â€œprecisely so they will not protect minority rightsâ€ with the vigor and scope that they have, Halbertal said. At the same time, not only is this election a struggle about the future of Israel, he said, but also â€œabout the future of Judaism in Israel. The Torah stands for the equality of all people and the notion that we are all created in Godâ€™s image. Israelis of all people need to respect minority rights because we, as Jews, know what it is to be a minorityâ€ â€” with and without rights. â€œThis is a deep Jewish ethos,â€ Halbertal added, â€œand it is now being challenged from within Israel itself. But, when you have these visceral security threats in the street every day, it becomes much easier for these ugly ideologies to anchor themselves.â€ This is going to have a profound effect on U.S.-Israel relations. But donâ€™t take my word for it. On Oct. 1, Axios published a story quoting what sources said Senator Bob Menendez, the New Jersey Democrat who leads the Foreign Relations Committee, told Netanyahu during a trip to Israel in September. In the words of one source, the senator warned that if Netanyahu formed a government after the Nov. 1 elections that included right-wing extremists, it could â€œseriously erode bipartisan support in Washington.â€ That is now about to happen. I have reported from Israel for this newspaper for nearly 40 years, often traveling around with my dear friend Nahum Barnea, one of the most respected, sober, balanced, careful journalists in the country. To hear him say to me minutes ago on the phone that â€œwe have a different kind of Israel nowâ€ tells me we are truly entering a dark tunnel. | G292: 0 | H292: 0 | I292: 1 | J292: 0 | K292: 1 | L292: 0 | M292: 1 | N292: 0 | O292: 0 | P292: 6 | Q292: 1558 | R292: 0.161 | S292: 0.416 | T292: 0.375 | U292: 0.215 | V292: 0.116 | W292: 0.5 | X292: 0.376 | Y292: 0.125 | Z292: 0.5 | AA292: 0.5 | AB292: 0.49 | AC292: 0.2885 | AD292: Title: The Israel We Knew Is Gone. Title: The Israel We Knew Is Gone. First Paragraph: Imagine you woke up after the 2024 U.S. presidential election and found that Donald Trump had been re-elected and chose Rudy Giuliani for attorney general, Michael Flynn for defense secretary, Steve Bannon for commerce secretary, evangelical leader James Dobson for education secretary, Proud Boys former leader Enrique Tarrio for homeland security head and Marjorie Taylor Greene for the White House spokeswoman. â€œImpossible,â€ you would say. Well, think again. As Iâ€™ve noted before, Israeli political trends are often a harbinger of wider trends in Western democracies â€” Off Broadway to our Broadway. I hoped that the national unity government that came to power in Israel in June 2021 might also be a harbinger of more bipartisanship here. Alas, that government has now collapsed and is being replaced by the most far-far-right coalition in Israelâ€™s history. Lord save us if this is a harbinger of whatâ€™s coming our way. The coalition that Likud leader Bibi Netanyahu is riding back into power is the Israeli equivalent of the nightmare U.S. cabinet I imagined above. Only it is real â€” a rowdy alliance of ultra-Orthodox leaders and ultranationalist politicians, including some outright racist, anti-Arab Jewish extremists once deemed completely outside the norms and boundaries of Israeli politics. As it is virtually impossible for Netanyahu to build a majority coalition without the support of these extremists, some of them are almost certain to be cabinet ministers in the next Israeli government. As that previously unthinkable reality takes hold, a fundamental question will roil synagogues in America and across the globe: â€œDo I support this Israel or not support it?â€ It will haunt pro-Israel students on college campuses. It will challenge Arab allies of Israel in the Abraham Accords, who just wanted to trade with Israel and never signed up for defending a government there that is anti-Israeli Arab. It will stress those U.S. diplomats who have reflexively defended Israel as a Jewish democracy that shares Americaâ€™s values, and it will send friends of Israel in Congress fleeing from any reporter asking if America should continue sending billions of dollars in aid to such a religious-extremist-inspired government. You have not seen this play before, because no Israeli leader has â€œgone thereâ€ before. Netanyahu has been propelled into power by bedfellows who: see Israeli Arab citizens as a fifth column who canâ€™t be trusted; have vowed to take political control over judicial appointments; believe that Jewish settlements must be expanded so there is not an inch left anywhere in the West Bank for a Palestinian state; want to enact judicial changes that could freeze Netanyahuâ€™s ongoing corruption trial; and express contempt for Israelâ€™s long and strong embrace of L.G.B.T.Q. rights. We are talking about people like Itamar Ben-Gvir, who was convicted by an Israeli court in 2007 of incitement to racism and supporting a Jewish terrorist organization. Netanyahu personally forged an alliance between Ben-Gvirâ€™s Jewish Power party and Bezalel Smotrich, the leader of the Religious Zionism party, which turned them (shockingly for many Israelis) into the third-largest party in the country â€” giving Netanyahu the allies Likud needed to win a parliamentary majority in this weekâ€™s election. Smotrich is known for, among other things, suggesting that Israeli Jewish mothers should be separated from Arab mothers in the maternity wards of Israeli hospitals. He has long advocated outright Israeli annexation of the West Bank and argued that there is â€œno such thing as Jewish terrorismâ€ when it comes to settlers retaliating on their own against Palestinian violence. Netanyahu has increasingly sought over the years to leverage the energy of this illiberal Israeli constituency to win office, not unlike how Trump uses white nationalism, but Netanyahu never actually brought this radical element â€” like Ben-Gvir, who claims to have moderated because he has told his supporters to chant, â€œDeath to terrorists,â€ instead of, â€œDeath to Arabsâ€ â€” into his ruling faction or cabinet. As more of Netanyahuâ€™s allies in Likud split with him over his alleged criminal behavior and lying, however, Bibi had to reach further and further out of the mainstream of Israeli politics to get enough votes to rule and pass a law to abort his own trial and possible jail time. Netanyahu had fertile political soil to work with, the Yediot Ahronot Israeli newspaper columnist Nahum Barnea explained to me. There has been a dramatic upsurge in violence â€” stabbings, shootings, gang warfare and organized crime â€” by Israeli Arabs against other Israeli Arabs, and Israeli Arab gangs and organized crime against Israeli Jews, particularly in mixed communities. The result is that, â€œlike in America, â€˜policingâ€™ has become a huge issue in Israel in recent years,â€ said Barnea â€” and even though this upsurge started when Netanyahu was previously prime minister, he and his anti-Arab allies blamed it all on the Arabs and the national unity Israeli government. One election billboard summed up Netanyahuâ€™s campaign. It was, as Haaretz reporter Amos Harel reported, a â€œgloomy-looking one with the caption: â€˜Thatâ€™s it. Weâ€™ve had enough.â€™ It depicts outgoing Prime Minister Yair Lapid and his coalition partner, Mansour Abbas of the United Arab List.â€ Abbas is the rather amazing Israeli Arab religious party leader who recognizes the State of Israel and the searing importance of the Holocaust, and who was part of the now-fallen unity government. As Harel put it: â€œThe â€˜had enoughâ€™ message seems to have sunk in among supporters of Likud, Religious Zionism and the ultra-Orthodox parties. Itâ€™s likely that the message also helped Netanyahu win Tuesdayâ€™s election.â€ Among the critical factors, Harel wrote, was â€œhatred of Arabs and the desire to keep them out of positions of power.â€ But Netanyahu was also aided by the fact that while the right and the far right were highly energized by both growing fears of and distrust of Arabs â€” whether Israeli Arab citizens or Palestinians in the West Bank â€” their centrist and center-left opponents had no coherent or inspiring countermessage. As Barnea put it to me: â€œIsrael is not divided down the middle,â€ with 50 percent being pro-Netanyahu and the other 50 percent with a unified message and strategy opposing him. â€œNo, Israel is divided between the 50 percent who are pro-Netanyahu and the 50 percent who are pro-blocking Netanyahu. But that is all they can agree on,â€ Barnea said. And it showed in this election. And it wasnâ€™t enough. Why is all of this so dangerous? Moshe Halbertal, the Hebrew University Jewish philosopher, captured it well: For decades members of the Israeli right, a vast majority of whom were â€œsecurity hawks,â€ have believed that the Palestinians have never and will never accept a Jewish state next to them and therefore Israel needed to take whatever military means were necessary to protect itself from them. But Israeli hawkishness toward the Palestinians, explained Halbertal, â€œis now morphing into something new â€” a kind of general ultranationalismâ€ that not only rejects any notion of a Palestinian state but also views every Israeli Arab â€” who make up about 21 percent of Israelâ€™s population, nearly 20 percent of its doctors, about 25 percent of its nurses and almost half its pharmacists â€” as a potential terrorist. â€œWhat we are seeing is a shift in the hawkish right from a political identity built on focusing on the â€˜enemy outsideâ€™ â€” the Palestinians â€” to the â€˜enemy insideâ€™ â€” Israeli Arabs,â€ Halbertal said. Netanyahuâ€™s coalition has also attacked the vital independent institutions that underpin Israelâ€™s democracy and are responsible for, among other things, protecting minority rights. That is, the lower court system, the media and, most of all, the Supreme Court, which Netanyahu and his allies want brought under the political control of the right, â€œprecisely so they will not protect minority rightsâ€ with the vigor and scope that they have, Halbertal said. At the same time, not only is this election a struggle about the future of Israel, he said, but also â€œabout the future of Judaism in Israel. The Torah stands for the equality of all people and the notion that we are all created in Godâ€™s image. Israelis of all people need to respect minority rights because we, as Jews, know what it is to be a minorityâ€ â€” with and without rights. â€œThis is a deep Jewish ethos,â€ Halbertal added, â€œand it is now being challenged from within Israel itself. But, when you have these visceral security threats in the street every day, it becomes much easier for these ugly ideologies to anchor themselves.â€ This is going to have a profound effect on U.S.-Israel relations. But donâ€™t take my word for it. On Oct. 1, Axios published a story quoting what sources said Senator Bob Menendez, the New Jersey Democrat who leads the Foreign Relations Committee, told Netanyahu during a trip to Israel in September. In the words of one source, the senator warned that if Netanyahu formed a government after the Nov. 1 elections that included right-wing extremists, it could â€œseriously erode bipartisan support in Washington.â€ That is now about to happen. I have reported from Israel for this newspaper for nearly 40 years, often traveling around with my dear friend Nahum Barnea, one of the most respected, sober, balanced, careful journalists in the country. To hear him say to me minutes ago on the phone that â€œwe have a different kind of Israel nowâ€ tells me we are truly entering a dark tunnel. | AE292: 44869 | AF292: 44869 | AG292: 2022 | AH292: israel | AI292: iran | AJ292: netanyahu
E296: Average built in excel | U296: =+AVERAGE(U2:U292) -> 0.43748454 | V296: =+AVERAGE(V2:V292) -> 0.47533677 | W296: =+AVERAGE(W2:W292) -> 0.32484192 | X296: =+AVERAGE(X2:X292) -> 0.34206529 | Y296: =+AVERAGE(Y2:Y292) -> 0.3995189 | Z296: =+AVERAGE(Z2:Z292) -> 0.34819244 | AA296: =+AVERAGE(AA2:AA292) -> 0.5 | AB296: =+AVERAGE(AB2:AB292) -> 0.48689347 | AC296: =+AVERAGE(AC2:AC292) -> 0.31361684

Sheet AuthSent
A1: # | B1: Author | C1: Article_Count | D1: Avg_Title_Sent | E1: Avg_First800_Sent | F1: Avg_Last4_Sent | G1: Avg_Netanyahu_Sent | H1: Avg_Hamas_Sent | I1: Avg_Palestinian_Sent | J1: Avg_Gaza_Sent | K1: Avg_Ceasefire_Sent | L1: Avg_Trump_Sent
A2: 0 | B2: Aaron Boxerman | C2: 9 | D2: 0.283889 | E2: 0.312333 | F2: 0.317333 | G2: 0.507444 | H2: 0.328222 | I2: 0.382556 | J2: 0.368333 | K2: 0.5 | L2: 0.507444
A3: 1 | B3: Adam Entous | C3: 1 | D3: 0.479 | E3: 0.52 | F3: 0.52 | G3: 0.5 | H3: 0.5 | I3: 0.537 | J3: 0.537 | K3: 0.5 | L3: 0.5
A4: 2 | B4: Adam Goldman | C4: 1 | D4: 0.374 | E4: 0.151 | F4: 0.398 | G4: 0.5 | H4: 0.149 | I4: 0.5 | J4: 0.254 | K4: 0.5 | L4: 0.5
A5: 3 | B5: Adam Rasgon | C5: 8 | D5: 0.278875 | E5: 0.406375 | F5: 0.4085 | G5: 0.5 | H5: 0.480125 | I5: 0.5 | J5: 0.455625 | K5: 0.5 | L5: 0.42275
A6: 4 | B6: Andrew Ross | C6: 1 | D6: 0.245 | E6: 0.101 | F6: 0.101 | G6: 0.5 | H6: 0.5 | I6: 0.419 | J6: 0.5 | K6: 0.5 | L6: 0.5
B8: Avg Built in Excel | G8: =+Data!U296 -> 0.43748454 | H8: =+Data!W296 -> 0.32484192 | I8: =+Data!Y296 -> 0.3995189 | J8: =+Data!Z296 -> 0.34819244 | K8: =+Data!AA296 -> 0.5

Sheet FriedmanTFIDF
A1: term | B1: tfidf_score | C1: interpretation
A2: israel | B2: 0.32753841 | C2: Distinctive â€” notable emphasis
A3: iran | B3: 0.21079483 | C3: Distinctive â€” notable emphasis
A4: netanyahu | B4: 0.17336765 | C4: Distinctive â€” notable emphasis
A5: gaza | B5: 0.17097704 | C5: Distinctive â€” notable emphasis
A6: hamas | B6: 0.16878645 | C6: Distinctive â€” notable emphasis
A7: saudi | B7: 0.15262307 | C7: Distinctive â€” notable emphasis
A8: war | B8: 0.15161526 | C8: Distinctive â€” notable emphasis
A9: israeli | B9: 0.15078852 | C9: Distinctive â€” notable emphasis
A10: will | B10: 0.14844245 | C10: Mildly distinctive â€” moderate emphasis
A11: authority | B11: 0.13109931 | C11: Mildly distinctive â€” moderate emphasis
A12: arab | B12: 0.12944433 | C12: Mildly distinctive â€” moderate emphasis
A13: palestinian | B13: 0.12918213 | C13: Mildly distinctive â€” moderate emphasis
... A41: state solution | B41: 0.064619973 | C41: Mildly distinctive â€” moderate emphasis

Sheet AuthTFIDF
B1: israel | C1: gaza | D1: west bank | E1: netanyahu | F1: hamas | G1: palestinian authority | H1: hezbollah | I1: iran | K1: israel | L1: gaza | M1: west bank | N1: netanyahu | O1: hamas | P1: palestinian authority | Q1: hezbollah | R1: iran | T1: israel | U1: gaza | V1: west bank | W1: netanyahu | X1: hamas | Y1: palestinian authority | Z1: hezbollah | AA1: iran
A2: Aaron Boxerman | B2: 0.2384097 | C2: 0.22473684 | D2: 0.042001033 | E2: 0.033135924 | F2: 0.14192588 | G2: 0 | H2: 0.015366463 | I2: 0.11846158 | K2: =+VALUE(B2) -> 0.2384097 | L2: =+VALUE(C2) -> 0.22473684 | M2: =+VALUE(D2) -> 0.042001033 | N2: =+VALUE(E2) -> 0.033135924 | O2: =+VALUE(F2) -> 0.14192588 | P2: =+VALUE(G2) -> 0 | Q2: =+VALUE(H2) -> 0.015366463 | R2: =+VALUE(I2) -> 0.11846158
A3: Adam Entous | B3: 0.040582247 | C3: 0.12751615 | D3: 0.19065178 | E3: 0 | F3: 0 | G3: 0 | H3: 0 | I3: 0.089620458 | K3: =+VALUE(B3) -> 0.040582247 | L3: =+VALUE(C3) -> 0.12751615 | M3: =+VALUE(D3) -> 0.19065178 | N3: =+VALUE(E3) -> 0 | O3: =+VALUE(F3) -> 0 | P3: =+VALUE(G3) -> 0 | Q3: =+VALUE(H3) -> 0 | R3: =+VALUE(I3) -> 0.089620458
A4: Adam Goldman | B4: 0.13186925 | C4: 0.13811835011653256 | D4: 0 | E4: 0 | F4: 0.18772238538784197 | G4: 0 | H4: 0 | I4: 0 | K4: =+VALUE(B4) -> 0.13186925 | L4: =+VALUE(C4) -> 0.13811835 | M4: =+VALUE(D4) -> 0 | N4: =+VALUE(E4) -> 0 | O4: =+VALUE(F4) -> 0.18772239 | P4: =+VALUE(G4) -> 0 | Q4: =+VALUE(H4) -> 0 | R4: =+VALUE(I4) -> 0
A5: Adam Rasgon | B5: 0.11209746 | C5: 0.26684001782084965 | D5: 0 | E5: 0 | F5: 0.13715646671476361 | G5: 0 | H5: 0 | I5: 0 | K5: =+VALUE(B5) -> 0.11209746 | L5: =+VALUE(C5) -> 0.26684002 | M5: =+VALUE(D5) -> 0 | N5: =+VALUE(E5) -> 0 | O5: =+VALUE(F5) -> 0.13715647 | P5: =+VALUE(G5) -> 0 | Q5: =+VALUE(H5) -> 0 | R5: =+VALUE(I5) -> 0
A6: Andrew Ross | B6: 0.12487607 | C6: 0.087195849 | D6: 0.097776109 | E6: 0 | F6: 0 | G6: 0 | H6: 0 | I6: 0 | K6: =+VALUE(B6) -> 0.12487607 | L6: =+VALUE(C6) -> 0.087195849 | M6: =+VALUE(D6) -> 0.097776109 | N6: =+VALUE(E6) -> 0 | O6: =+VALUE(F6) -> 0 | P6: =+VALUE(G6) -> 0 | Q6: =+VALUE(H6) -> 0 | R6: =+VALUE(I6) -> 0
A7: Andrew Ross Sorkin | B7: 0.071897323 | C7: 0.15060887491930014 | D7: 0 | E7: 0 | F7: 0.074435919 | G7: 0 | H7: 0 | I7: 0 | K7: =+VALUE(B7) -> 0.071897323 | L7: =+VALUE(C7) -> 0.15060887 | M7: =+VALUE(D7) -> 0 | N7: =+VALUE(E7) -> 0 | O7: =+VALUE(F7) -> 0.074435919 | P7: =+VALUE(G7) -> 0 | Q7: =+VALUE(H7) -> 0 | R7: =+VALUE(I7) -> 0
A8: Anemona Hartocollis | B8: 0.051030563281349486 | C8: 0.026724415627264853 | D8: 0 | E8: 0 | F8: 0.044026986 | G8: 0 | H8: 0 | I8: 0 | K8: =+VALUE(B8) -> 0.051030563 | L8: =+VALUE(C8) -> 0.026724416 | M8: =+VALUE(D8) -> 0 | N8: =+VALUE(E8) -> 0 | O8: =+VALUE(F8) -> 0.044026986 | P8: =+VALUE(G8) -> 0 | Q8: =+VALUE(H8) -> 0 | R8: =+VALUE(I8) -> 0
A9: Aurelien Breeden | B9: 0.14294646610526668 | C9: 0.029944100374389215 | D9: 0 | E9: 0.1059613095131413 | F9: 0.1479937102908324 | G9: 0 | H9: 0 | I9: 0 | K9: =+VALUE(B9) -> 0.14294647 | L9: =+VALUE(C9) -> 0.0299441 | M9: =+VALUE(D9) -> 0 | N9: =+VALUE(E9) -> 0.10596131 | O9: =+VALUE(F9) -> 0.14799371 | P9: =+VALUE(G9) -> 0 | Q9: =+VALUE(H9) -> 0 | R9: =+VALUE(I9) -> 0
A10: Ben Hubbard | B10: 0.17124436684002575 | C10: 0.05380782 | D10: 0 | E10: 0 | F10: 0.070916308 | G10: 0 | H10: 0.4414955000635276 | I10: 0.018908513 | K10: =+VALUE(B10) -> 0.17124437 | L10: =+VALUE(C10) -> 0.05380782 | M10: =+VALUE(D10) -> 0 | N10: =+VALUE(E10) -> 0 | O10: =+VALUE(F10) -> 0.070916308 | P10: =+VALUE(G10) -> 0 | Q10: =+VALUE(H10) -> 0.4414955 | R10: =+VALUE(I10) -> 0.018908513
A11: Benzion Sanders | B11: 0.034248962 | C11: 0.14348789246212462 | D11: 0.053632858291935905 | E11: 0 | F11: 0.15365239962859412 | G11: 0 | H11: 0 | I11: 0 | K11: =+VALUE(B11) -> 0.034248962 | L11: =+VALUE(C11) -> 0.14348789 | M11: =+VALUE(D11) -> 0.053632858 | N11: =+VALUE(E11) -> 0 | O11: =+VALUE(F11) -> 0.1536524 | P11: =+VALUE(G11) -> 0 | Q11: =+VALUE(H11) -> 0 | R11: =+VALUE(I11) -> 0
A12: Bernie Sanders | B12: 0.17053729948588936 | C12: 0.10206790101252157 | D12: 0.076301814 | E12: 0.045147659786577705 | F12: 0.092483149 | G12: 0.025081527505934387 | H12: 0 | I12: 0 | K12: =+VALUE(B12) -> 0.1705373 | L12: =+VALUE(C12) -> 0.1020679 | M12: =+VALUE(D12) -> 0.076301814 | N12: =+VALUE(E12) -> 0.04514766 | O12: =+VALUE(F12) -> 0.092483149 | P12: =+VALUE(G12) -> 0.025081528 | Q12: =+VALUE(H12) -> 0 | R12: =+VALUE(I12) -> 0
A13: Binod Ghimire | B13: 0 | C13: 0.064593743 | D13: 0 | E13: 0 | F13: 0.12769751128626397 | G13: 0 | H13: 0 | I13: 0 | K13: =+VALUE(B13) -> 0 | L13: =+VALUE(C13) -> 0.064593743 | M13: =+VALUE(D13) -> 0 | N13: =+VALUE(E13) -> 0 | O13: =+VALUE(F13) -> 0.12769751 | P13: =+VALUE(G13) -> 0 | Q13: =+VALUE(H13) -> 0 | R13: =+VALUE(I13) -> 0
A14: Bret Stephens | B14: 0.3370922906227746 | C14: 0.11915998732045152 | D14: 0 | E14: 0.085894513 | F14: 0.16140998321616531 | G14: 0.013014058 | H14: 0.08690781 | I14: 0.074442319 | K14: =+VALUE(B14) -> 0.33709229 | L14: =+VALUE(C14) -> 0.11915999 | M14: =+VALUE(D14) -> 0 | N14: =+VALUE(E14) -> 0.085894513 | O14: =+VALUE(F14) -> 0.16140998 | P14: =+VALUE(G14) -> 0.013014058 | Q14: =+VALUE(H14) -> 0.08690781 | R14: =+VALUE(I14) -> 0.074442319
A15: Cassandra Vinograd | B15: 0.013907081 | C15: 0.087396708 | D15: 0 | E15: 0 | F15: 0.057592483 | G15: 0 | H15: 0 | I15: 0 | K15: =+VALUE(B15) -> 0.013907081 | L15: =+VALUE(C15) -> 0.087396708 | M15: =+VALUE(D15) -> 0 | N15: =+VALUE(E15) -> 0 | O15: =+VALUE(F15) -> 0.057592483 | P15: =+VALUE(G15) -> 0 | Q15: =+VALUE(H15) -> 0 | R15: =+VALUE(I15) -> 0
